[
  {
    "timestamp": "2026-06-05T23:59:06.490Z",
    "simTime": "Dia 4 - 8:48 AM",
    "dailyCost": 1,
    "totalCost": 13.448754260396942,
    "totalRevenue": 563.355952785771,
    "profit": 549.907198525374
  },
  {
    "timestamp": "2026-06-05T23:59:08.490Z",
    "simTime": "Dia 4 - 8:54 AM",
    "dailyCost": 1,
    "totalCost": 13.465354788337073,
    "totalRevenue": 563.355952785771,
    "profit": 549.8905979974339
  },
  {
    "timestamp": "2026-06-05T23:59:10.505Z",
    "simTime": "Dia 4 - 9:00 AM",
    "dailyCost": 1,
    "totalCost": 13.481955835865486,
    "totalRevenue": 563.355952785771,
    "profit": 549.8739969499055
  },
  {
    "timestamp": "2026-06-05T23:59:12.523Z",
    "simTime": "Dia 4 - 9:06 AM",
    "dailyCost": 1,
    "totalCost": 13.498557618202693,
    "totalRevenue": 563.355952785771,
    "profit": 549.8573951675684
  },
  {
    "timestamp": "2026-06-05T23:59:14.538Z",
    "simTime": "Dia 4 - 9:12 AM",
    "dailyCost": 1,
    "totalCost": 13.515160135348694,
    "totalRevenue": 563.355952785771,
    "profit": 549.8407926504224
  },
  {
    "timestamp": "2026-06-05T23:59:16.554Z",
    "simTime": "Dia 4 - 9:18 AM",
    "dailyCost": 1,
    "totalCost": 13.531763387303489,
    "totalRevenue": 563.355952785771,
    "profit": 549.8241893984675
  },
  {
    "timestamp": "2026-06-05T23:59:18.571Z",
    "simTime": "Dia 4 - 9:24 AM",
    "dailyCost": 1,
    "totalCost": 13.548367374067077,
    "totalRevenue": 563.355952785771,
    "profit": 549.8075854117039
  },
  {
    "timestamp": "2026-06-05T23:59:20.574Z",
    "simTime": "Dia 4 - 9:30 AM",
    "dailyCost": 1,
    "totalCost": 13.56497209563946,
    "totalRevenue": 563.355952785771,
    "profit": 549.7909806901316
  },
  {
    "timestamp": "2026-06-05T23:59:22.579Z",
    "simTime": "Dia 4 - 9:36 AM",
    "dailyCost": 1,
    "totalCost": 13.581577552020637,
    "totalRevenue": 563.355952785771,
    "profit": 549.7743752337503
  },
  {
    "timestamp": "2026-06-05T23:59:24.590Z",
    "simTime": "Dia 4 - 9:42 AM",
    "dailyCost": 1,
    "totalCost": 13.598183743210607,
    "totalRevenue": 563.355952785771,
    "profit": 549.7577690425604
  },
  {
    "timestamp": "2026-06-05T23:59:26.597Z",
    "simTime": "Dia 4 - 9:48 AM",
    "dailyCost": 1,
    "totalCost": 13.614790669209372,
    "totalRevenue": 563.355952785771,
    "profit": 549.7411621165617
  },
  {
    "timestamp": "2026-06-05T23:59:28.611Z",
    "simTime": "Dia 4 - 9:54 AM",
    "dailyCost": 1,
    "totalCost": 13.63139833001693,
    "totalRevenue": 563.355952785771,
    "profit": 549.7245544557541
  },
  {
    "timestamp": "2026-06-05T23:59:30.615Z",
    "simTime": "Dia 4 - 10:00 AM",
    "dailyCost": 1,
    "totalCost": 13.648006725633282,
    "totalRevenue": 563.355952785771,
    "profit": 549.7079460601377
  },
  {
    "timestamp": "2026-06-05T23:59:32.626Z",
    "simTime": "Dia 4 - 10:06 AM",
    "dailyCost": 1,
    "totalCost": 13.664616021202937,
    "totalRevenue": 563.355952785771,
    "profit": 549.6913367645681
  },
  {
    "timestamp": "2026-06-05T23:59:34.641Z",
    "simTime": "Dia 4 - 10:12 AM",
    "dailyCost": 1,
    "totalCost": 13.681226216725893,
    "totalRevenue": 563.355952785771,
    "profit": 549.6747265690451
  },
  {
    "timestamp": "2026-06-05T23:59:36.643Z",
    "simTime": "Dia 4 - 10:18 AM",
    "dailyCost": 1,
    "totalCost": 13.697837312202152,
    "totalRevenue": 563.355952785771,
    "profit": 549.6581154735688
  },
  {
    "timestamp": "2026-06-05T23:59:38.654Z",
    "simTime": "Dia 4 - 10:24 AM",
    "dailyCost": 1,
    "totalCost": 13.714449307631712,
    "totalRevenue": 563.355952785771,
    "profit": 549.6415034781393
  },
  {
    "timestamp": "2026-06-05T23:59:40.669Z",
    "simTime": "Dia 4 - 10:30 AM",
    "dailyCost": 1,
    "totalCost": 13.731062203014574,
    "totalRevenue": 563.355952785771,
    "profit": 549.6248905827565
  },
  {
    "timestamp": "2026-06-05T23:59:42.671Z",
    "simTime": "Dia 4 - 10:36 AM",
    "dailyCost": 1,
    "totalCost": 13.747675998350738,
    "totalRevenue": 563.355952785771,
    "profit": 549.6082767874203
  },
  {
    "timestamp": "2026-06-05T23:59:44.675Z",
    "simTime": "Dia 4 - 10:42 AM",
    "dailyCost": 1,
    "totalCost": 13.764290693640204,
    "totalRevenue": 563.355952785771,
    "profit": 549.5916620921308
  },
  {
    "timestamp": "2026-06-05T23:59:46.692Z",
    "simTime": "Dia 4 - 10:48 AM",
    "dailyCost": 1,
    "totalCost": 13.780906288882973,
    "totalRevenue": 563.355952785771,
    "profit": 549.575046496888
  },
  {
    "timestamp": "2026-06-05T23:59:48.692Z",
    "simTime": "Dia 4 - 10:54 AM",
    "dailyCost": 1,
    "totalCost": 13.797522784079042,
    "totalRevenue": 563.355952785771,
    "profit": 549.5584300016919
  },
  {
    "timestamp": "2026-06-05T23:59:50.692Z",
    "simTime": "Dia 4 - 11:00 AM",
    "dailyCost": 1,
    "totalCost": 13.814140179228414,
    "totalRevenue": 563.355952785771,
    "profit": 549.5418126065426
  },
  {
    "timestamp": "2026-06-05T23:59:52.712Z",
    "simTime": "Dia 4 - 11:06 AM",
    "dailyCost": 1,
    "totalCost": 13.830758578145264,
    "totalRevenue": 563.355952785771,
    "profit": 549.5251942076258
  },
  {
    "timestamp": "2026-06-05T23:59:54.712Z",
    "simTime": "Dia 4 - 11:12 AM",
    "dailyCost": 1,
    "totalCost": 13.847377980829595,
    "totalRevenue": 563.355952785771,
    "profit": 549.5085748049414
  },
  {
    "timestamp": "2026-06-05T23:59:56.727Z",
    "simTime": "Dia 4 - 11:18 AM",
    "dailyCost": 1,
    "totalCost": 13.863998387281406,
    "totalRevenue": 563.355952785771,
    "profit": 549.4919543984896
  },
  {
    "timestamp": "2026-06-05T23:59:58.728Z",
    "simTime": "Dia 4 - 11:24 AM",
    "dailyCost": 1,
    "totalCost": 13.880619797500696,
    "totalRevenue": 563.355952785771,
    "profit": 549.4753329882703
  },
  {
    "timestamp": "2026-06-06T00:00:00.738Z",
    "simTime": "Dia 4 - 11:30 AM",
    "dailyCost": 1,
    "totalCost": 13.897242211487464,
    "totalRevenue": 563.355952785771,
    "profit": 549.4587105742836
  },
  {
    "timestamp": "2026-06-06T00:00:02.745Z",
    "simTime": "Dia 4 - 11:36 AM",
    "dailyCost": 1,
    "totalCost": 13.913865629241712,
    "totalRevenue": 563.355952785771,
    "profit": 549.4420871565293
  },
  {
    "timestamp": "2026-06-06T00:00:04.745Z",
    "simTime": "Dia 4 - 11:42 AM",
    "dailyCost": 1,
    "totalCost": 13.93049005076344,
    "totalRevenue": 563.355952785771,
    "profit": 549.4254627350076
  },
  {
    "timestamp": "2026-06-06T00:00:06.745Z",
    "simTime": "Dia 4 - 11:48 AM",
    "dailyCost": 1,
    "totalCost": 13.947115476052648,
    "totalRevenue": 563.355952785771,
    "profit": 549.4088373097184
  },
  {
    "timestamp": "2026-06-06T00:00:08.756Z",
    "simTime": "Dia 4 - 11:54 AM",
    "dailyCost": 1,
    "totalCost": 13.963741905109336,
    "totalRevenue": 563.355952785771,
    "profit": 549.3922108806617
  },
  {
    "timestamp": "2026-06-06T00:00:10.761Z",
    "simTime": "Dia 4 - 12:00 PM",
    "dailyCost": 1,
    "totalCost": 13.980369337933503,
    "totalRevenue": 563.355952785771,
    "profit": 549.3755834478375
  },
  {
    "timestamp": "2026-06-06T00:00:12.761Z",
    "simTime": "Dia 4 - 12:06 PM",
    "dailyCost": 1,
    "totalCost": 13.996997809934232,
    "totalRevenue": 563.355952785771,
    "profit": 549.3589549758368
  },
  {
    "timestamp": "2026-06-06T00:00:14.776Z",
    "simTime": "Dia 4 - 12:12 PM",
    "dailyCost": 1,
    "totalCost": 14.013627321111523,
    "totalRevenue": 563.355952785771,
    "profit": 549.3423254646596
  },
  {
    "timestamp": "2026-06-06T00:00:16.793Z",
    "simTime": "Dia 4 - 12:18 PM",
    "dailyCost": 1,
    "totalCost": 14.030257871465377,
    "totalRevenue": 563.355952785771,
    "profit": 549.3256949143057
  },
  {
    "timestamp": "2026-06-06T00:00:18.797Z",
    "simTime": "Dia 4 - 12:24 PM",
    "dailyCost": 1,
    "totalCost": 14.046889460995793,
    "totalRevenue": 563.355952785771,
    "profit": 549.3090633247753
  },
  {
    "timestamp": "2026-06-06T00:00:20.814Z",
    "simTime": "Dia 4 - 12:30 PM",
    "dailyCost": 1,
    "totalCost": 14.06352208970277,
    "totalRevenue": 563.355952785771,
    "profit": 549.2924306960682
  },
  {
    "timestamp": "2026-06-06T00:00:22.814Z",
    "simTime": "Dia 4 - 12:36 PM",
    "dailyCost": 1,
    "totalCost": 14.08015575758631,
    "totalRevenue": 563.355952785771,
    "profit": 549.2757970281847
  },
  {
    "timestamp": "2026-06-06T00:00:24.814Z",
    "simTime": "Dia 4 - 12:42 PM",
    "dailyCost": 1,
    "totalCost": 14.096790464646412,
    "totalRevenue": 563.355952785771,
    "profit": 549.2591623211246
  },
  {
    "timestamp": "2026-06-06T00:00:26.814Z",
    "simTime": "Dia 4 - 12:48 PM",
    "dailyCost": 1,
    "totalCost": 14.113426210883077,
    "totalRevenue": 563.355952785771,
    "profit": 549.242526574888
  },
  {
    "timestamp": "2026-06-06T00:00:28.814Z",
    "simTime": "Dia 4 - 12:54 PM",
    "dailyCost": 1,
    "totalCost": 14.130062996296303,
    "totalRevenue": 563.355952785771,
    "profit": 549.2258897894748
  },
  {
    "timestamp": "2026-06-06T00:00:30.814Z",
    "simTime": "Dia 4 - 1:00 PM",
    "dailyCost": 1,
    "totalCost": 14.146700820886092,
    "totalRevenue": 563.355952785771,
    "profit": 549.209251964885
  },
  {
    "timestamp": "2026-06-06T00:00:32.828Z",
    "simTime": "Dia 4 - 1:06 PM",
    "dailyCost": 1,
    "totalCost": 14.16333964924336,
    "totalRevenue": 563.355952785771,
    "profit": 549.1926131365277
  },
  {
    "timestamp": "2026-06-06T00:00:34.830Z",
    "simTime": "Dia 4 - 1:12 PM",
    "dailyCost": 1,
    "totalCost": 14.179979481368107,
    "totalRevenue": 563.355952785771,
    "profit": 549.1759733044029
  },
  {
    "timestamp": "2026-06-06T00:00:36.830Z",
    "simTime": "Dia 4 - 1:18 PM",
    "dailyCost": 1,
    "totalCost": 14.196620317260335,
    "totalRevenue": 563.355952785771,
    "profit": 549.1593324685107
  },
  {
    "timestamp": "2026-06-06T00:00:38.845Z",
    "simTime": "Dia 4 - 1:24 PM",
    "dailyCost": 1,
    "totalCost": 14.213262156920042,
    "totalRevenue": 563.355952785771,
    "profit": 549.142690628851
  },
  {
    "timestamp": "2026-06-06T00:00:40.848Z",
    "simTime": "Dia 4 - 1:30 PM",
    "dailyCost": 1,
    "totalCost": 14.229905000347228,
    "totalRevenue": 563.355952785771,
    "profit": 549.1260477854238
  },
  {
    "timestamp": "2026-06-06T00:00:42.853Z",
    "simTime": "Dia 4 - 1:36 PM",
    "dailyCost": 1,
    "totalCost": 14.246548847541895,
    "totalRevenue": 563.355952785771,
    "profit": 549.1094039382291
  },
  {
    "timestamp": "2026-06-06T00:00:44.863Z",
    "simTime": "Dia 4 - 1:42 PM",
    "dailyCost": 1,
    "totalCost": 14.263193698504042,
    "totalRevenue": 563.355952785771,
    "profit": 549.0927590872669
  },
  {
    "timestamp": "2026-06-06T00:00:46.877Z",
    "simTime": "Dia 4 - 1:48 PM",
    "dailyCost": 1,
    "totalCost": 14.279839553233666,
    "totalRevenue": 563.355952785771,
    "profit": 549.0761132325374
  },
  {
    "timestamp": "2026-06-06T00:00:48.877Z",
    "simTime": "Dia 4 - 1:54 PM",
    "dailyCost": 1,
    "totalCost": 14.29648641173077,
    "totalRevenue": 563.355952785771,
    "profit": 549.0594663740402
  },
  {
    "timestamp": "2026-06-06T00:00:50.896Z",
    "simTime": "Dia 4 - 2:00 PM",
    "dailyCost": 1,
    "totalCost": 14.313134273995354,
    "totalRevenue": 563.355952785771,
    "profit": 549.0428185117756
  },
  {
    "timestamp": "2026-06-06T00:00:52.897Z",
    "simTime": "Dia 4 - 2:06 PM",
    "dailyCost": 1,
    "totalCost": 14.32978303621324,
    "totalRevenue": 563.355952785771,
    "profit": 549.0261697495578
  },
  {
    "timestamp": "2026-06-06T00:00:54.916Z",
    "simTime": "Dia 4 - 2:12 PM",
    "dailyCost": 1,
    "totalCost": 14.346432698384428,
    "totalRevenue": 563.355952785771,
    "profit": 549.0095200873866
  },
  {
    "timestamp": "2026-06-06T00:00:56.916Z",
    "simTime": "Dia 4 - 2:18 PM",
    "dailyCost": 1,
    "totalCost": 14.363083260508917,
    "totalRevenue": 563.355952785771,
    "profit": 548.9928695252621
  },
  {
    "timestamp": "2026-06-06T00:00:58.922Z",
    "simTime": "Dia 4 - 2:24 PM",
    "dailyCost": 1,
    "totalCost": 14.37973472258671,
    "totalRevenue": 563.355952785771,
    "profit": 548.9762180631843
  },
  {
    "timestamp": "2026-06-06T00:01:00.932Z",
    "simTime": "Dia 4 - 2:30 PM",
    "dailyCost": 1,
    "totalCost": 14.396387084617803,
    "totalRevenue": 563.355952785771,
    "profit": 548.9595657011532
  },
  {
    "timestamp": "2026-06-06T00:01:02.938Z",
    "simTime": "Dia 4 - 2:36 PM",
    "dailyCost": 1,
    "totalCost": 14.413040346602198,
    "totalRevenue": 563.355952785771,
    "profit": 548.9429124391688
  },
  {
    "timestamp": "2026-06-06T00:01:04.939Z",
    "simTime": "Dia 4 - 2:42 PM",
    "dailyCost": 1,
    "totalCost": 14.429694508539896,
    "totalRevenue": 563.355952785771,
    "profit": 548.9262582772311
  },
  {
    "timestamp": "2026-06-06T00:01:06.952Z",
    "simTime": "Dia 4 - 2:48 PM",
    "dailyCost": 1,
    "totalCost": 14.446349570430895,
    "totalRevenue": 563.355952785771,
    "profit": 548.9096032153401
  },
  {
    "timestamp": "2026-06-06T00:01:08.964Z",
    "simTime": "Dia 4 - 2:54 PM",
    "dailyCost": 1,
    "totalCost": 14.463005532275195,
    "totalRevenue": 563.355952785771,
    "profit": 548.8929472534958
  },
  {
    "timestamp": "2026-06-06T00:01:10.967Z",
    "simTime": "Dia 4 - 3:00 PM",
    "dailyCost": 1,
    "totalCost": 14.479662394072799,
    "totalRevenue": 563.355952785771,
    "profit": 548.8762903916983
  },
  {
    "timestamp": "2026-06-06T00:01:12.979Z",
    "simTime": "Dia 4 - 3:06 PM",
    "dailyCost": 1,
    "totalCost": 14.496319990679195,
    "totalRevenue": 563.355952785771,
    "profit": 548.8596327950918
  },
  {
    "timestamp": "2026-06-06T00:01:14.987Z",
    "simTime": "Dia 4 - 3:12 PM",
    "dailyCost": 1,
    "totalCost": 14.512978322094387,
    "totalRevenue": 563.355952785771,
    "profit": 548.8429744636767
  },
  {
    "timestamp": "2026-06-06T00:01:16.987Z",
    "simTime": "Dia 4 - 3:18 PM",
    "dailyCost": 1,
    "totalCost": 14.529637388318372,
    "totalRevenue": 563.355952785771,
    "profit": 548.8263153974526
  },
  {
    "timestamp": "2026-06-06T00:01:18.987Z",
    "simTime": "Dia 4 - 3:24 PM",
    "dailyCost": 1,
    "totalCost": 14.54629718935115,
    "totalRevenue": 563.355952785771,
    "profit": 548.8096555964198
  },
  {
    "timestamp": "2026-06-06T00:01:21.003Z",
    "simTime": "Dia 4 - 3:30 PM",
    "dailyCost": 1,
    "totalCost": 14.562957725192724,
    "totalRevenue": 563.355952785771,
    "profit": 548.7929950605783
  },
  {
    "timestamp": "2026-06-06T00:01:23.004Z",
    "simTime": "Dia 4 - 3:36 PM",
    "dailyCost": 1,
    "totalCost": 14.579618995843092,
    "totalRevenue": 563.355952785771,
    "profit": 548.7763337899279
  },
  {
    "timestamp": "2026-06-06T00:01:25.013Z",
    "simTime": "Dia 4 - 3:42 PM",
    "dailyCost": 1,
    "totalCost": 14.596281001302252,
    "totalRevenue": 563.355952785771,
    "profit": 548.7596717844688
  },
  {
    "timestamp": "2026-06-06T00:01:27.018Z",
    "simTime": "Dia 4 - 3:48 PM",
    "dailyCost": 1,
    "totalCost": 14.612943741570207,
    "totalRevenue": 563.355952785771,
    "profit": 548.7430090442008
  },
  {
    "timestamp": "2026-06-06T00:01:29.022Z",
    "simTime": "Dia 4 - 3:54 PM",
    "dailyCost": 1,
    "totalCost": 14.629607216646956,
    "totalRevenue": 563.355952785771,
    "profit": 548.7263455691241
  },
  {
    "timestamp": "2026-06-06T00:01:31.033Z",
    "simTime": "Dia 4 - 4:00 PM",
    "dailyCost": 1,
    "totalCost": 14.646271426532499,
    "totalRevenue": 563.355952785771,
    "profit": 548.7096813592385
  },
  {
    "timestamp": "2026-06-06T00:01:33.038Z",
    "simTime": "Dia 4 - 4:06 PM",
    "dailyCost": 1,
    "totalCost": 14.662936156006323,
    "totalRevenue": 563.355952785771,
    "profit": 548.6930166297647
  },
  {
    "timestamp": "2026-06-06T00:01:35.038Z",
    "simTime": "Dia 4 - 4:12 PM",
    "dailyCost": 1,
    "totalCost": 14.679601405068428,
    "totalRevenue": 563.355952785771,
    "profit": 548.6763513807026
  },
  {
    "timestamp": "2026-06-06T00:01:37.053Z",
    "simTime": "Dia 4 - 4:18 PM",
    "dailyCost": 1,
    "totalCost": 14.696267173718814,
    "totalRevenue": 563.355952785771,
    "profit": 548.6596856120522
  },
  {
    "timestamp": "2026-06-06T00:01:39.054Z",
    "simTime": "Dia 4 - 4:24 PM",
    "dailyCost": 1,
    "totalCost": 14.712933461957482,
    "totalRevenue": 563.355952785771,
    "profit": 548.6430193238135
  },
  {
    "timestamp": "2026-06-06T00:01:41.054Z",
    "simTime": "Dia 4 - 4:30 PM",
    "dailyCost": 1,
    "totalCost": 14.72960026978443,
    "totalRevenue": 563.355952785771,
    "profit": 548.6263525159866
  },
  {
    "timestamp": "2026-06-06T00:01:43.055Z",
    "simTime": "Dia 4 - 4:36 PM",
    "dailyCost": 1,
    "totalCost": 14.74626759719966,
    "totalRevenue": 563.355952785771,
    "profit": 548.6096851885713
  },
  {
    "timestamp": "2026-06-06T00:01:45.068Z",
    "simTime": "Dia 4 - 4:42 PM",
    "dailyCost": 1,
    "totalCost": 14.76293544420317,
    "totalRevenue": 563.355952785771,
    "profit": 548.5930173415678
  },
  {
    "timestamp": "2026-06-06T00:01:47.071Z",
    "simTime": "Dia 4 - 4:48 PM",
    "dailyCost": 1,
    "totalCost": 14.779603810794963,
    "totalRevenue": 563.355952785771,
    "profit": 548.5763489749761
  },
  {
    "timestamp": "2026-06-06T00:01:49.072Z",
    "simTime": "Dia 4 - 4:54 PM",
    "dailyCost": 1,
    "totalCost": 14.796272696975036,
    "totalRevenue": 563.355952785771,
    "profit": 548.559680088796
  },
  {
    "timestamp": "2026-06-06T00:01:51.072Z",
    "simTime": "Dia 4 - 5:00 PM",
    "dailyCost": 1,
    "totalCost": 14.81294210274339,
    "totalRevenue": 563.355952785771,
    "profit": 548.5430106830277
  },
  {
    "timestamp": "2026-06-06T00:01:53.089Z",
    "simTime": "Dia 4 - 5:06 PM",
    "dailyCost": 1,
    "totalCost": 14.82961177747043,
    "totalRevenue": 563.355952785771,
    "profit": 548.5263410083006
  },
  {
    "timestamp": "2026-06-06T00:01:55.104Z",
    "simTime": "Dia 4 - 5:12 PM",
    "dailyCost": 1,
    "totalCost": 14.846281721156155,
    "totalRevenue": 563.355952785771,
    "profit": 548.5096710646148
  },
  {
    "timestamp": "2026-06-06T00:01:57.119Z",
    "simTime": "Dia 4 - 5:18 PM",
    "dailyCost": 1,
    "totalCost": 14.862951933800565,
    "totalRevenue": 563.355952785771,
    "profit": 548.4930008519705
  },
  {
    "timestamp": "2026-06-06T00:01:59.122Z",
    "simTime": "Dia 4 - 5:24 PM",
    "dailyCost": 1,
    "totalCost": 14.879622415403661,
    "totalRevenue": 563.355952785771,
    "profit": 548.4763303703674
  },
  {
    "timestamp": "2026-06-06T00:02:01.123Z",
    "simTime": "Dia 4 - 5:30 PM",
    "dailyCost": 1,
    "totalCost": 14.896293165965442,
    "totalRevenue": 563.355952785771,
    "profit": 548.4596596198056
  },
  {
    "timestamp": "2026-06-06T00:02:03.138Z",
    "simTime": "Dia 4 - 5:36 PM",
    "dailyCost": 1,
    "totalCost": 14.91296418548591,
    "totalRevenue": 563.355952785771,
    "profit": 548.4429886002852
  },
  {
    "timestamp": "2026-06-06T00:02:05.138Z",
    "simTime": "Dia 4 - 5:42 PM",
    "dailyCost": 1,
    "totalCost": 14.929635473965062,
    "totalRevenue": 563.355952785771,
    "profit": 548.426317311806
  },
  {
    "timestamp": "2026-06-06T00:02:07.153Z",
    "simTime": "Dia 4 - 5:48 PM",
    "dailyCost": 1,
    "totalCost": 14.9463070314029,
    "totalRevenue": 563.355952785771,
    "profit": 548.4096457543682
  },
  {
    "timestamp": "2026-06-06T00:02:09.166Z",
    "simTime": "Dia 4 - 5:54 PM",
    "dailyCost": 1,
    "totalCost": 14.962978857799424,
    "totalRevenue": 563.355952785771,
    "profit": 548.3929739279716
  },
  {
    "timestamp": "2026-06-06T00:02:11.170Z",
    "simTime": "Dia 4 - 6:00 PM",
    "dailyCost": 1,
    "totalCost": 14.979650953154634,
    "totalRevenue": 563.355952785771,
    "profit": 548.3763018326164
  },
  {
    "timestamp": "2026-06-06T00:02:13.176Z",
    "simTime": "Dia 4 - 6:06 PM",
    "dailyCost": 1,
    "totalCost": 14.996323048509844,
    "totalRevenue": 563.355952785771,
    "profit": 548.3596297372612
  },
  {
    "timestamp": "2026-06-06T00:02:15.190Z",
    "simTime": "Dia 4 - 6:12 PM",
    "dailyCost": 1,
    "totalCost": 15.012995143865053,
    "totalRevenue": 563.355952785771,
    "profit": 548.342957641906
  },
  {
    "timestamp": "2026-06-06T00:02:17.191Z",
    "simTime": "Dia 4 - 6:18 PM",
    "dailyCost": 1,
    "totalCost": 15.029667239220263,
    "totalRevenue": 563.355952785771,
    "profit": 548.3262855465507
  },
  {
    "timestamp": "2026-06-06T00:02:19.190Z",
    "simTime": "Dia 4 - 6:24 PM",
    "dailyCost": 1,
    "totalCost": 15.046339334575473,
    "totalRevenue": 563.355952785771,
    "profit": 548.3096134511956
  },
  {
    "timestamp": "2026-06-06T00:02:21.206Z",
    "simTime": "Dia 4 - 6:30 PM",
    "dailyCost": 1,
    "totalCost": 15.063011429930683,
    "totalRevenue": 563.355952785771,
    "profit": 548.2929413558403
  },
  {
    "timestamp": "2026-06-06T00:02:23.206Z",
    "simTime": "Dia 4 - 6:36 PM",
    "dailyCost": 1,
    "totalCost": 15.079683525285892,
    "totalRevenue": 563.355952785771,
    "profit": 548.2762692604852
  },
  {
    "timestamp": "2026-06-06T00:02:25.223Z",
    "simTime": "Dia 4 - 6:42 PM",
    "dailyCost": 1,
    "totalCost": 15.096355620641102,
    "totalRevenue": 563.355952785771,
    "profit": 548.2595971651299
  },
  {
    "timestamp": "2026-06-06T00:02:27.223Z",
    "simTime": "Dia 4 - 6:48 PM",
    "dailyCost": 1,
    "totalCost": 15.113027715996312,
    "totalRevenue": 563.355952785771,
    "profit": 548.2429250697747
  },
  {
    "timestamp": "2026-06-06T00:02:29.227Z",
    "simTime": "Dia 4 - 6:54 PM",
    "dailyCost": 1,
    "totalCost": 15.129699811351522,
    "totalRevenue": 563.355952785771,
    "profit": 548.2262529744195
  },
  {
    "timestamp": "2026-06-06T00:02:31.238Z",
    "simTime": "Dia 4 - 7:00 PM",
    "dailyCost": 1,
    "totalCost": 15.146371906706731,
    "totalRevenue": 563.355952785771,
    "profit": 548.2095808790643
  },
  {
    "timestamp": "2026-06-06T00:02:33.243Z",
    "simTime": "Dia 4 - 7:06 PM",
    "dailyCost": 1,
    "totalCost": 15.163043733103255,
    "totalRevenue": 563.355952785771,
    "profit": 548.1929090526678
  },
  {
    "timestamp": "2026-06-06T00:02:35.253Z",
    "simTime": "Dia 4 - 7:12 PM",
    "dailyCost": 1,
    "totalCost": 15.179715290541093,
    "totalRevenue": 563.355952785771,
    "profit": 548.1762374952299
  },
  {
    "timestamp": "2026-06-06T00:02:37.262Z",
    "simTime": "Dia 4 - 7:18 PM",
    "dailyCost": 1,
    "totalCost": 15.196386579020245,
    "totalRevenue": 563.355952785771,
    "profit": 548.1595662067508
  },
  {
    "timestamp": "2026-06-06T00:02:39.269Z",
    "simTime": "Dia 4 - 7:24 PM",
    "dailyCost": 1,
    "totalCost": 15.213057598540713,
    "totalRevenue": 563.355952785771,
    "profit": 548.1428951872304
  },
  {
    "timestamp": "2026-06-06T00:02:41.275Z",
    "simTime": "Dia 4 - 7:30 PM",
    "dailyCost": 1,
    "totalCost": 15.229728349102494,
    "totalRevenue": 563.355952785771,
    "profit": 548.1262244366685
  },
  {
    "timestamp": "2026-06-06T00:02:43.292Z",
    "simTime": "Dia 4 - 7:36 PM",
    "dailyCost": 1,
    "totalCost": 15.24639883070559,
    "totalRevenue": 563.355952785771,
    "profit": 548.1095539550654
  },
  {
    "timestamp": "2026-06-06T00:02:45.292Z",
    "simTime": "Dia 4 - 7:42 PM",
    "dailyCost": 1,
    "totalCost": 15.26306904335,
    "totalRevenue": 563.355952785771,
    "profit": 548.092883742421
  },
  {
    "timestamp": "2026-06-06T00:02:47.292Z",
    "simTime": "Dia 4 - 7:48 PM",
    "dailyCost": 1,
    "totalCost": 15.279738987035726,
    "totalRevenue": 563.355952785771,
    "profit": 548.0762137987354
  },
  {
    "timestamp": "2026-06-06T00:02:49.303Z",
    "simTime": "Dia 4 - 7:54 PM",
    "dailyCost": 1,
    "totalCost": 15.296408661762765,
    "totalRevenue": 563.355952785771,
    "profit": 548.0595441240083
  },
  {
    "timestamp": "2026-06-06T00:02:51.312Z",
    "simTime": "Dia 4 - 8:00 PM",
    "dailyCost": 1,
    "totalCost": 15.31307806753112,
    "totalRevenue": 563.355952785771,
    "profit": 548.0428747182399
  },
  {
    "timestamp": "2026-06-06T00:02:53.324Z",
    "simTime": "Dia 4 - 8:06 PM",
    "dailyCost": 1,
    "totalCost": 15.329746953711192,
    "totalRevenue": 563.355952785771,
    "profit": 548.0262058320599
  },
  {
    "timestamp": "2026-06-06T00:02:55.329Z",
    "simTime": "Dia 4 - 8:12 PM",
    "dailyCost": 1,
    "totalCost": 15.346415320302984,
    "totalRevenue": 563.355952785771,
    "profit": 548.009537465468
  },
  {
    "timestamp": "2026-06-06T00:02:57.347Z",
    "simTime": "Dia 4 - 8:18 PM",
    "dailyCost": 1,
    "totalCost": 15.363083167306495,
    "totalRevenue": 563.355952785771,
    "profit": 547.9928696184645
  },
  {
    "timestamp": "2026-06-06T00:02:59.360Z",
    "simTime": "Dia 4 - 8:24 PM",
    "dailyCost": 1,
    "totalCost": 15.379750494721725,
    "totalRevenue": 563.355952785771,
    "profit": 547.9762022910493
  },
  {
    "timestamp": "2026-06-06T00:03:01.375Z",
    "simTime": "Dia 4 - 8:30 PM",
    "dailyCost": 1,
    "totalCost": 15.396417302548674,
    "totalRevenue": 563.355952785771,
    "profit": 547.9595354832223
  },
  {
    "timestamp": "2026-06-06T00:03:03.379Z",
    "simTime": "Dia 4 - 8:36 PM",
    "dailyCost": 1,
    "totalCost": 15.413083590787341,
    "totalRevenue": 563.355952785771,
    "profit": 547.9428691949837
  },
  {
    "timestamp": "2026-06-06T00:03:05.393Z",
    "simTime": "Dia 4 - 8:42 PM",
    "dailyCost": 1,
    "totalCost": 15.429749359437727,
    "totalRevenue": 563.355952785771,
    "profit": 547.9262034263332
  },
  {
    "timestamp": "2026-06-06T00:03:07.393Z",
    "simTime": "Dia 4 - 8:48 PM",
    "dailyCost": 1,
    "totalCost": 15.446414608499833,
    "totalRevenue": 563.355952785771,
    "profit": 547.9095381772712
  },
  {
    "timestamp": "2026-06-06T00:03:09.413Z",
    "simTime": "Dia 4 - 8:54 PM",
    "dailyCost": 1,
    "totalCost": 15.463079337973657,
    "totalRevenue": 563.355952785771,
    "profit": 547.8928734477973
  },
  {
    "timestamp": "2026-06-06T00:03:11.414Z",
    "simTime": "Dia 4 - 9:00 PM",
    "dailyCost": 1,
    "totalCost": 15.479743547859199,
    "totalRevenue": 563.355952785771,
    "profit": 547.8762092379118
  },
  {
    "timestamp": "2026-06-06T00:03:13.428Z",
    "simTime": "Dia 4 - 9:06 PM",
    "dailyCost": 1,
    "totalCost": 15.496407022935948,
    "totalRevenue": 563.355952785771,
    "profit": 547.8595457628351
  },
  {
    "timestamp": "2026-06-06T00:03:15.430Z",
    "simTime": "Dia 4 - 9:12 PM",
    "dailyCost": 1,
    "totalCost": 15.513069763203903,
    "totalRevenue": 563.355952785771,
    "profit": 547.8428830225671
  },
  {
    "timestamp": "2026-06-06T00:03:17.445Z",
    "simTime": "Dia 4 - 9:18 PM",
    "dailyCost": 1,
    "totalCost": 15.529731768663064,
    "totalRevenue": 563.355952785771,
    "profit": 547.826221017108
  },
  {
    "timestamp": "2026-06-06T00:03:19.446Z",
    "simTime": "Dia 4 - 9:24 PM",
    "dailyCost": 1,
    "totalCost": 15.54639303931343,
    "totalRevenue": 563.355952785771,
    "profit": 547.8095597464576
  },
  {
    "timestamp": "2026-06-06T00:03:21.458Z",
    "simTime": "Dia 4 - 9:30 PM",
    "dailyCost": 1,
    "totalCost": 15.563053575155005,
    "totalRevenue": 563.355952785771,
    "profit": 547.792899210616
  },
  {
    "timestamp": "2026-06-06T00:03:23.463Z",
    "simTime": "Dia 4 - 9:36 PM",
    "dailyCost": 1,
    "totalCost": 15.579713376187783,
    "totalRevenue": 563.355952785771,
    "profit": 547.7762394095832
  },
  {
    "timestamp": "2026-06-06T00:03:25.476Z",
    "simTime": "Dia 4 - 9:42 PM",
    "dailyCost": 1,
    "totalCost": 15.596372442411768,
    "totalRevenue": 563.355952785771,
    "profit": 547.7595803433593
  },
  {
    "timestamp": "2026-06-06T00:03:27.477Z",
    "simTime": "Dia 4 - 9:48 PM",
    "dailyCost": 1,
    "totalCost": 15.61303077382696,
    "totalRevenue": 563.355952785771,
    "profit": 547.7429220119441
  },
  {
    "timestamp": "2026-06-06T00:03:29.494Z",
    "simTime": "Dia 4 - 9:54 PM",
    "dailyCost": 1,
    "totalCost": 15.629688370433357,
    "totalRevenue": 563.355952785771,
    "profit": 547.7262644153377
  },
  {
    "timestamp": "2026-06-06T00:03:31.514Z",
    "simTime": "Dia 4 - 10:00 PM",
    "dailyCost": 1,
    "totalCost": 15.64634523223096,
    "totalRevenue": 563.355952785771,
    "profit": 547.7096075535401
  },
  {
    "timestamp": "2026-06-06T00:03:33.515Z",
    "simTime": "Dia 4 - 10:06 PM",
    "dailyCost": 1,
    "totalCost": 15.66300119407526,
    "totalRevenue": 563.355952785771,
    "profit": 547.6929515916958
  },
  {
    "timestamp": "2026-06-06T00:03:35.527Z",
    "simTime": "Dia 4 - 10:12 PM",
    "dailyCost": 1,
    "totalCost": 15.67965625596626,
    "totalRevenue": 563.355952785771,
    "profit": 547.6762965298047
  },
  {
    "timestamp": "2026-06-06T00:03:37.545Z",
    "simTime": "Dia 4 - 10:18 PM",
    "dailyCost": 1,
    "totalCost": 15.696310417903957,
    "totalRevenue": 563.355952785771,
    "profit": 547.659642367867
  },
  {
    "timestamp": "2026-06-06T00:03:39.557Z",
    "simTime": "Dia 4 - 10:24 PM",
    "dailyCost": 1,
    "totalCost": 15.712963679888352,
    "totalRevenue": 563.355952785771,
    "profit": 547.6429891058826
  },
  {
    "timestamp": "2026-06-06T00:03:41.559Z",
    "simTime": "Dia 4 - 10:30 PM",
    "dailyCost": 1,
    "totalCost": 15.729616041919446,
    "totalRevenue": 563.355952785771,
    "profit": 547.6263367438515
  },
  {
    "timestamp": "2026-06-06T00:03:43.574Z",
    "simTime": "Dia 4 - 10:36 PM",
    "dailyCost": 1,
    "totalCost": 15.746267503997238,
    "totalRevenue": 563.355952785771,
    "profit": 547.6096852817737
  },
  {
    "timestamp": "2026-06-06T00:03:45.595Z",
    "simTime": "Dia 4 - 10:42 PM",
    "dailyCost": 1,
    "totalCost": 15.762918066121728,
    "totalRevenue": 563.355952785771,
    "profit": 547.5930347196493
  },
  {
    "timestamp": "2026-06-06T00:03:47.601Z",
    "simTime": "Dia 4 - 10:48 PM",
    "dailyCost": 1,
    "totalCost": 15.779567728292916,
    "totalRevenue": 563.355952785771,
    "profit": 547.5763850574781
  },
  {
    "timestamp": "2026-06-06T00:03:49.612Z",
    "simTime": "Dia 4 - 10:54 PM",
    "dailyCost": 1,
    "totalCost": 15.796216490510801,
    "totalRevenue": 563.355952785771,
    "profit": 547.5597362952602
  },
  {
    "timestamp": "2026-06-06T00:03:51.616Z",
    "simTime": "Dia 4 - 11:00 PM",
    "dailyCost": 1,
    "totalCost": 15.812864352775385,
    "totalRevenue": 563.355952785771,
    "profit": 547.5430884329957
  },
  {
    "timestamp": "2026-06-06T00:03:53.616Z",
    "simTime": "Dia 4 - 11:06 PM",
    "dailyCost": 1,
    "totalCost": 15.82951121127249,
    "totalRevenue": 563.355952785771,
    "profit": 547.5264415744986
  },
  {
    "timestamp": "2026-06-06T00:03:55.616Z",
    "simTime": "Dia 4 - 11:12 PM",
    "dailyCost": 1,
    "totalCost": 15.846157066002114,
    "totalRevenue": 563.355952785771,
    "profit": 547.5097957197689
  },
  {
    "timestamp": "2026-06-06T00:03:57.629Z",
    "simTime": "Dia 4 - 11:18 PM",
    "dailyCost": 1,
    "totalCost": 15.86280191696426,
    "totalRevenue": 563.355952785771,
    "profit": 547.4931508688068
  },
  {
    "timestamp": "2026-06-06T00:03:59.643Z",
    "simTime": "Dia 4 - 11:24 PM",
    "dailyCost": 1,
    "totalCost": 15.879445764158927,
    "totalRevenue": 563.355952785771,
    "profit": 547.4765070216121
  },
  {
    "timestamp": "2026-06-06T00:04:01.651Z",
    "simTime": "Dia 4 - 11:30 PM",
    "dailyCost": 1,
    "totalCost": 15.896088607586114,
    "totalRevenue": 563.355952785771,
    "profit": 547.459864178185
  },
  {
    "timestamp": "2026-06-06T00:04:03.663Z",
    "simTime": "Dia 4 - 11:36 PM",
    "dailyCost": 1,
    "totalCost": 15.91273044724582,
    "totalRevenue": 563.355952785771,
    "profit": 547.4432223385252
  },
  {
    "timestamp": "2026-06-06T00:04:05.664Z",
    "simTime": "Dia 4 - 11:42 PM",
    "dailyCost": 1,
    "totalCost": 15.929371283138048,
    "totalRevenue": 563.355952785771,
    "profit": 547.426581502633
  },
  {
    "timestamp": "2026-06-06T00:04:07.669Z",
    "simTime": "Dia 4 - 11:48 PM",
    "dailyCost": 1,
    "totalCost": 15.946011115262795,
    "totalRevenue": 563.355952785771,
    "profit": 547.4099416705083
  },
  {
    "timestamp": "2026-06-06T00:04:09.675Z",
    "simTime": "Dia 4 - 11:54 PM",
    "dailyCost": 1,
    "totalCost": 15.962649943620063,
    "totalRevenue": 563.355952785771,
    "profit": 547.393302842151
  },
  {
    "timestamp": "2026-06-06T00:04:11.679Z",
    "simTime": "Dia 5 - 12:00 AM",
    "dailyCost": 1,
    "totalCost": 15.979287768209852,
    "totalRevenue": 563.355952785771,
    "profit": 547.3766650175612
  },
  {
    "timestamp": "2026-06-06T00:04:13.697Z",
    "simTime": "Dia 5 - 12:06 AM",
    "dailyCost": 1,
    "totalCost": 15.995924553623079,
    "totalRevenue": 563.355952785771,
    "profit": 547.3600282321479
  },
  {
    "timestamp": "2026-06-06T00:04:15.703Z",
    "simTime": "Dia 5 - 12:12 AM",
    "dailyCost": 1,
    "totalCost": 16.012560299859743,
    "totalRevenue": 563.355952785771,
    "profit": 547.3433924859113
  },
  {
    "timestamp": "2026-06-06T00:04:17.717Z",
    "simTime": "Dia 5 - 12:18 AM",
    "dailyCost": 1,
    "totalCost": 16.029195006919846,
    "totalRevenue": 563.355952785771,
    "profit": 547.3267577788512
  },
  {
    "timestamp": "2026-06-06T00:04:19.723Z",
    "simTime": "Dia 5 - 12:24 AM",
    "dailyCost": 1,
    "totalCost": 16.045828674803385,
    "totalRevenue": 563.355952785771,
    "profit": 547.3101241109676
  },
  {
    "timestamp": "2026-06-06T00:04:21.729Z",
    "simTime": "Dia 5 - 12:30 AM",
    "dailyCost": 1,
    "totalCost": 16.051543713865886,
    "totalRevenue": 67.5,
    "profit": 51.44845628613412
  },
  {
    "timestamp": "2026-06-06T00:04:23.744Z",
    "simTime": "Dia 5 - 12:36 AM",
    "dailyCost": 1,
    "totalCost": 16.05720389859896,
    "totalRevenue": 67.5,
    "profit": 51.44279610140104
  },
  {
    "timestamp": "2026-06-06T00:04:25.746Z",
    "simTime": "Dia 5 - 12:42 AM",
    "dailyCost": 1,
    "totalCost": 16.062863958820316,
    "totalRevenue": 67.5,
    "profit": 51.437136041179684
  },
  {
    "timestamp": "2026-06-06T00:04:27.746Z",
    "simTime": "Dia 5 - 12:48 AM",
    "dailyCost": 1,
    "totalCost": 16.06738479215365,
    "totalRevenue": 67.5,
    "profit": 51.432615207846354
  },
  {
    "timestamp": "2026-06-06T00:04:29.748Z",
    "simTime": "Dia 5 - 12:54 AM",
    "dailyCost": 1,
    "totalCost": 16.073044603351565,
    "totalRevenue": 67.5,
    "profit": 51.42695539664844
  },
  {
    "timestamp": "2026-06-06T00:04:31.764Z",
    "simTime": "Dia 5 - 1:00 AM",
    "dailyCost": 2,
    "totalCost": 16.08287095670443,
    "totalRevenue": 67.5,
    "profit": 51.417129043295574
  },
  {
    "timestamp": "2026-06-06T00:04:33.766Z",
    "simTime": "Dia 5 - 1:06 AM",
    "dailyCost": 2,
    "totalCost": 16.092697189788208,
    "totalRevenue": 67.5,
    "profit": 51.40730281021179
  },
  {
    "timestamp": "2026-06-06T00:04:35.766Z",
    "simTime": "Dia 5 - 1:12 AM",
    "dailyCost": 2,
    "totalCost": 16.102523302602904,
    "totalRevenue": 67.5,
    "profit": 51.397476697397096
  },
  {
    "timestamp": "2026-06-06T00:04:37.778Z",
    "simTime": "Dia 5 - 1:18 AM",
    "dailyCost": 2,
    "totalCost": 16.112349295148515,
    "totalRevenue": 67.5,
    "profit": 51.38765070485148
  },
  {
    "timestamp": "2026-06-06T00:04:39.782Z",
    "simTime": "Dia 5 - 1:24 AM",
    "dailyCost": 2,
    "totalCost": 16.12217516742504,
    "totalRevenue": 67.5,
    "profit": 51.37782483257496
  },
  {
    "timestamp": "2026-06-06T00:04:41.788Z",
    "simTime": "Dia 5 - 1:30 AM",
    "dailyCost": 2,
    "totalCost": 16.132000919432482,
    "totalRevenue": 67.5,
    "profit": 51.367999080567515
  },
  {
    "timestamp": "2026-06-06T00:04:43.804Z",
    "simTime": "Dia 5 - 1:36 AM",
    "dailyCost": 2,
    "totalCost": 16.141826551170837,
    "totalRevenue": 67.5,
    "profit": 51.35817344882916
  },
  {
    "timestamp": "2026-06-06T00:04:45.805Z",
    "simTime": "Dia 5 - 1:42 AM",
    "dailyCost": 2,
    "totalCost": 16.151652062640107,
    "totalRevenue": 67.5,
    "profit": 51.34834793735989
  },
  {
    "timestamp": "2026-06-06T00:04:47.820Z",
    "simTime": "Dia 5 - 1:48 AM",
    "dailyCost": 2,
    "totalCost": 16.16147745384029,
    "totalRevenue": 67.5,
    "profit": 51.33852254615971
  },
  {
    "timestamp": "2026-06-06T00:04:49.821Z",
    "simTime": "Dia 5 - 1:54 AM",
    "dailyCost": 2,
    "totalCost": 16.171302724771394,
    "totalRevenue": 67.5,
    "profit": 51.328697275228606
  },
  {
    "timestamp": "2026-06-06T00:04:51.835Z",
    "simTime": "Dia 5 - 2:00 AM",
    "dailyCost": 2,
    "totalCost": 16.18112787543341,
    "totalRevenue": 67.5,
    "profit": 51.31887212456659
  },
  {
    "timestamp": "2026-06-06T00:04:53.840Z",
    "simTime": "Dia 5 - 2:06 AM",
    "dailyCost": 2,
    "totalCost": 16.190952918265115,
    "totalRevenue": 67.5,
    "profit": 51.30904708173489
  },
  {
    "timestamp": "2026-06-06T00:04:55.854Z",
    "simTime": "Dia 5 - 2:12 AM",
    "dailyCost": 2,
    "totalCost": 16.20077785326651,
    "totalRevenue": 67.5,
    "profit": 51.29922214673349
  },
  {
    "timestamp": "2026-06-06T00:04:57.869Z",
    "simTime": "Dia 5 - 2:18 AM",
    "dailyCost": 2,
    "totalCost": 16.21060268043759,
    "totalRevenue": 67.5,
    "profit": 51.28939731956241
  },
  {
    "timestamp": "2026-06-06T00:04:59.877Z",
    "simTime": "Dia 5 - 2:24 AM",
    "dailyCost": 2,
    "totalCost": 16.22042739977836,
    "totalRevenue": 67.5,
    "profit": 51.27957260022164
  },
  {
    "timestamp": "2026-06-06T00:05:01.884Z",
    "simTime": "Dia 5 - 2:30 AM",
    "dailyCost": 2,
    "totalCost": 16.23025201128882,
    "totalRevenue": 67.5,
    "profit": 51.26974798871118
  },
  {
    "timestamp": "2026-06-06T00:05:03.890Z",
    "simTime": "Dia 5 - 2:36 AM",
    "dailyCost": 2,
    "totalCost": 16.240076514968965,
    "totalRevenue": 67.5,
    "profit": 51.25992348503104
  },
  {
    "timestamp": "2026-06-06T00:05:05.905Z",
    "simTime": "Dia 5 - 2:42 AM",
    "dailyCost": 2,
    "totalCost": 16.249900910818802,
    "totalRevenue": 67.5,
    "profit": 51.2500990891812
  },
  {
    "timestamp": "2026-06-06T00:05:07.920Z",
    "simTime": "Dia 5 - 2:48 AM",
    "dailyCost": 2,
    "totalCost": 16.259725198838325,
    "totalRevenue": 67.5,
    "profit": 51.240274801161675
  },
  {
    "timestamp": "2026-06-06T00:05:09.923Z",
    "simTime": "Dia 5 - 2:54 AM",
    "dailyCost": 2,
    "totalCost": 16.269549379027538,
    "totalRevenue": 67.5,
    "profit": 51.23045062097246
  },
  {
    "timestamp": "2026-06-06T00:05:11.936Z",
    "simTime": "Dia 5 - 3:00 AM",
    "dailyCost": 2,
    "totalCost": 16.27937345138644,
    "totalRevenue": 67.5,
    "profit": 51.22062654861356
  },
  {
    "timestamp": "2026-06-06T00:05:13.936Z",
    "simTime": "Dia 5 - 3:06 AM",
    "dailyCost": 2,
    "totalCost": 16.28919743570226,
    "totalRevenue": 67.5,
    "profit": 51.21080256429774
  },
  {
    "timestamp": "2026-06-06T00:05:15.938Z",
    "simTime": "Dia 5 - 3:12 AM",
    "dailyCost": 2,
    "totalCost": 16.299021331975,
    "totalRevenue": 67.5,
    "profit": 51.200978668025
  },
  {
    "timestamp": "2026-06-06T00:05:17.949Z",
    "simTime": "Dia 5 - 3:18 AM",
    "dailyCost": 2,
    "totalCost": 16.308845140204657,
    "totalRevenue": 67.5,
    "profit": 51.19115485979535
  },
  {
    "timestamp": "2026-06-06T00:05:19.962Z",
    "simTime": "Dia 5 - 3:24 AM",
    "dailyCost": 2,
    "totalCost": 16.318668860391234,
    "totalRevenue": 67.5,
    "profit": 51.181331139608766
  },
  {
    "timestamp": "2026-06-06T00:05:21.967Z",
    "simTime": "Dia 5 - 3:30 AM",
    "dailyCost": 2,
    "totalCost": 16.328492492534732,
    "totalRevenue": 67.5,
    "profit": 51.171507507465265
  },
  {
    "timestamp": "2026-06-06T00:05:23.973Z",
    "simTime": "Dia 5 - 3:36 AM",
    "dailyCost": 2,
    "totalCost": 16.33831603663515,
    "totalRevenue": 67.5,
    "profit": 51.16168396336485
  },
  {
    "timestamp": "2026-06-06T00:05:25.980Z",
    "simTime": "Dia 5 - 3:42 AM",
    "dailyCost": 2,
    "totalCost": 16.348139492692486,
    "totalRevenue": 67.5,
    "profit": 51.15186050730752
  },
  {
    "timestamp": "2026-06-06T00:05:27.984Z",
    "simTime": "Dia 5 - 3:48 AM",
    "dailyCost": 2,
    "totalCost": 16.357962860706742,
    "totalRevenue": 67.5,
    "profit": 51.14203713929326
  },
  {
    "timestamp": "2026-06-06T00:05:29.985Z",
    "simTime": "Dia 5 - 3:54 AM",
    "dailyCost": 2,
    "totalCost": 16.367786140677918,
    "totalRevenue": 67.5,
    "profit": 51.13221385932208
  },
  {
    "timestamp": "2026-06-06T00:05:32.000Z",
    "simTime": "Dia 5 - 4:00 AM",
    "dailyCost": 2,
    "totalCost": 16.377609332606013,
    "totalRevenue": 67.5,
    "profit": 51.12239066739399
  },
  {
    "timestamp": "2026-06-06T00:05:34.009Z",
    "simTime": "Dia 5 - 4:06 AM",
    "dailyCost": 2,
    "totalCost": 16.387432462278248,
    "totalRevenue": 67.5,
    "profit": 51.11256753772175
  },
  {
    "timestamp": "2026-06-06T00:05:36.024Z",
    "simTime": "Dia 5 - 4:12 AM",
    "dailyCost": 2,
    "totalCost": 16.397255529694625,
    "totalRevenue": 67.5,
    "profit": 51.102744470305375
  },
  {
    "timestamp": "2026-06-06T00:05:38.028Z",
    "simTime": "Dia 5 - 4:18 AM",
    "dailyCost": 2,
    "totalCost": 16.407078534855142,
    "totalRevenue": 67.5,
    "profit": 51.092921465144855
  },
  {
    "timestamp": "2026-06-06T00:05:40.029Z",
    "simTime": "Dia 5 - 4:24 AM",
    "dailyCost": 2,
    "totalCost": 16.416901477759797,
    "totalRevenue": 67.5,
    "profit": 51.083098522240206
  },
  {
    "timestamp": "2026-06-06T00:05:42.030Z",
    "simTime": "Dia 5 - 4:30 AM",
    "dailyCost": 2,
    "totalCost": 16.426724358408595,
    "totalRevenue": 67.5,
    "profit": 51.07327564159141
  },
  {
    "timestamp": "2026-06-06T00:05:44.031Z",
    "simTime": "Dia 5 - 4:36 AM",
    "dailyCost": 2,
    "totalCost": 16.436547176801533,
    "totalRevenue": 67.5,
    "profit": 51.06345282319847
  },
  {
    "timestamp": "2026-06-06T00:05:46.031Z",
    "simTime": "Dia 5 - 4:42 AM",
    "dailyCost": 2,
    "totalCost": 16.446369932938612,
    "totalRevenue": 67.5,
    "profit": 51.05363006706139
  },
  {
    "timestamp": "2026-06-06T00:05:48.042Z",
    "simTime": "Dia 5 - 4:48 AM",
    "dailyCost": 2,
    "totalCost": 16.45619262681983,
    "totalRevenue": 67.5,
    "profit": 51.04380737318017
  },
  {
    "timestamp": "2026-06-06T00:05:50.042Z",
    "simTime": "Dia 5 - 4:54 AM",
    "dailyCost": 2,
    "totalCost": 16.466015258445193,
    "totalRevenue": 67.5,
    "profit": 51.033984741554804
  },
  {
    "timestamp": "2026-06-06T00:05:52.047Z",
    "simTime": "Dia 5 - 5:00 AM",
    "dailyCost": 2,
    "totalCost": 16.475837827814694,
    "totalRevenue": 67.5,
    "profit": 51.02416217218531
  },
  {
    "timestamp": "2026-06-06T00:05:54.048Z",
    "simTime": "Dia 5 - 5:06 AM",
    "dailyCost": 2,
    "totalCost": 16.48566036495819,
    "totalRevenue": 67.5,
    "profit": 51.01433963504181
  },
  {
    "timestamp": "2026-06-06T00:05:56.050Z",
    "simTime": "Dia 5 - 5:12 AM",
    "dailyCost": 2,
    "totalCost": 16.495482869875683,
    "totalRevenue": 67.5,
    "profit": 51.00451713012431
  },
  {
    "timestamp": "2026-06-06T00:05:58.054Z",
    "simTime": "Dia 5 - 5:18 AM",
    "dailyCost": 2,
    "totalCost": 16.505305342567173,
    "totalRevenue": 67.5,
    "profit": 50.99469465743283
  },
  {
    "timestamp": "2026-06-06T00:06:00.062Z",
    "simTime": "Dia 5 - 5:24 AM",
    "dailyCost": 2,
    "totalCost": 16.515127783032657,
    "totalRevenue": 67.5,
    "profit": 50.98487221696735
  },
  {
    "timestamp": "2026-06-06T00:06:02.068Z",
    "simTime": "Dia 5 - 5:30 AM",
    "dailyCost": 2,
    "totalCost": 16.524950191272136,
    "totalRevenue": 67.5,
    "profit": 50.97504980872786
  },
  {
    "timestamp": "2026-06-06T00:06:04.073Z",
    "simTime": "Dia 5 - 5:36 AM",
    "dailyCost": 2,
    "totalCost": 16.53477256728561,
    "totalRevenue": 67.5,
    "profit": 50.965227432714386
  },
  {
    "timestamp": "2026-06-06T00:06:06.075Z",
    "simTime": "Dia 5 - 5:42 AM",
    "dailyCost": 2,
    "totalCost": 16.544594911073084,
    "totalRevenue": 67.5,
    "profit": 50.955405088926916
  },
  {
    "timestamp": "2026-06-06T00:06:08.089Z",
    "simTime": "Dia 5 - 5:48 AM",
    "dailyCost": 2,
    "totalCost": 16.55441722263455,
    "totalRevenue": 67.5,
    "profit": 50.945582777365445
  },
  {
    "timestamp": "2026-06-06T00:06:10.093Z",
    "simTime": "Dia 5 - 5:54 AM",
    "dailyCost": 2,
    "totalCost": 16.564239501970015,
    "totalRevenue": 67.5,
    "profit": 50.935760498029985
  },
  {
    "timestamp": "2026-06-06T00:06:12.095Z",
    "simTime": "Dia 5 - 6:00 AM",
    "dailyCost": 2,
    "totalCost": 16.574061749079473,
    "totalRevenue": 67.5,
    "profit": 50.925938250920524
  },
  {
    "timestamp": "2026-06-06T00:06:14.104Z",
    "simTime": "Dia 5 - 6:06 AM",
    "dailyCost": 2,
    "totalCost": 16.58388399618893,
    "totalRevenue": 67.5,
    "profit": 50.91611600381107
  },
  {
    "timestamp": "2026-06-06T00:06:16.107Z",
    "simTime": "Dia 5 - 6:12 AM",
    "dailyCost": 2,
    "totalCost": 16.59370624329839,
    "totalRevenue": 67.5,
    "profit": 50.906293756701615
  },
  {
    "timestamp": "2026-06-06T00:06:18.109Z",
    "simTime": "Dia 5 - 6:18 AM",
    "dailyCost": 2,
    "totalCost": 16.603528490407847,
    "totalRevenue": 67.5,
    "profit": 50.89647150959215
  },
  {
    "timestamp": "2026-06-06T00:06:20.113Z",
    "simTime": "Dia 5 - 6:24 AM",
    "dailyCost": 2,
    "totalCost": 16.613350737517305,
    "totalRevenue": 67.5,
    "profit": 50.88664926248269
  },
  {
    "timestamp": "2026-06-06T00:06:22.115Z",
    "simTime": "Dia 5 - 6:30 AM",
    "dailyCost": 2,
    "totalCost": 16.623172984626763,
    "totalRevenue": 67.5,
    "profit": 50.87682701537324
  },
  {
    "timestamp": "2026-06-06T00:06:24.120Z",
    "simTime": "Dia 5 - 6:36 AM",
    "dailyCost": 2,
    "totalCost": 16.63299523173622,
    "totalRevenue": 67.5,
    "profit": 50.86700476826378
  },
  {
    "timestamp": "2026-06-06T00:06:26.130Z",
    "simTime": "Dia 5 - 6:42 AM",
    "dailyCost": 2,
    "totalCost": 16.64281747884568,
    "totalRevenue": 67.5,
    "profit": 50.85718252115432
  },
  {
    "timestamp": "2026-06-06T00:06:28.143Z",
    "simTime": "Dia 5 - 6:48 AM",
    "dailyCost": 2,
    "totalCost": 16.652639725955137,
    "totalRevenue": 67.5,
    "profit": 50.84736027404486
  },
  {
    "timestamp": "2026-06-06T00:06:30.143Z",
    "simTime": "Dia 5 - 6:54 AM",
    "dailyCost": 2,
    "totalCost": 16.662461973064595,
    "totalRevenue": 67.5,
    "profit": 50.837538026935405
  },
  {
    "timestamp": "2026-06-06T00:06:32.146Z",
    "simTime": "Dia 5 - 7:00 AM",
    "dailyCost": 2,
    "totalCost": 16.672284220174053,
    "totalRevenue": 67.5,
    "profit": 50.82771577982595
  },
  {
    "timestamp": "2026-06-06T00:06:34.160Z",
    "simTime": "Dia 5 - 7:06 AM",
    "dailyCost": 2,
    "totalCost": 16.682106499509516,
    "totalRevenue": 67.5,
    "profit": 50.817893500490484
  },
  {
    "timestamp": "2026-06-06T00:06:36.169Z",
    "simTime": "Dia 5 - 7:12 AM",
    "dailyCost": 2,
    "totalCost": 16.691928811070984,
    "totalRevenue": 67.5,
    "profit": 50.80807118892902
  },
  {
    "timestamp": "2026-06-06T00:06:38.176Z",
    "simTime": "Dia 5 - 7:18 AM",
    "dailyCost": 2,
    "totalCost": 16.701751154858457,
    "totalRevenue": 67.5,
    "profit": 50.79824884514154
  },
  {
    "timestamp": "2026-06-06T00:06:40.178Z",
    "simTime": "Dia 5 - 7:24 AM",
    "dailyCost": 2,
    "totalCost": 16.71157353087193,
    "totalRevenue": 67.5,
    "profit": 50.78842646912807
  },
  {
    "timestamp": "2026-06-06T00:06:42.181Z",
    "simTime": "Dia 5 - 7:30 AM",
    "dailyCost": 2,
    "totalCost": 16.72139593911141,
    "totalRevenue": 67.5,
    "profit": 50.77860406088859
  },
  {
    "timestamp": "2026-06-06T00:06:44.189Z",
    "simTime": "Dia 5 - 7:36 AM",
    "dailyCost": 2,
    "totalCost": 16.731218379576895,
    "totalRevenue": 67.5,
    "profit": 50.768781620423105
  },
  {
    "timestamp": "2026-06-06T00:06:46.191Z",
    "simTime": "Dia 5 - 7:42 AM",
    "dailyCost": 2,
    "totalCost": 16.741040852268384,
    "totalRevenue": 67.5,
    "profit": 50.758959147731616
  },
  {
    "timestamp": "2026-06-06T00:06:48.200Z",
    "simTime": "Dia 5 - 7:48 AM",
    "dailyCost": 2,
    "totalCost": 16.750863357185878,
    "totalRevenue": 67.5,
    "profit": 50.74913664281412
  },
  {
    "timestamp": "2026-06-06T00:06:50.205Z",
    "simTime": "Dia 5 - 7:54 AM",
    "dailyCost": 2,
    "totalCost": 16.760685894329374,
    "totalRevenue": 67.5,
    "profit": 50.73931410567063
  },
  {
    "timestamp": "2026-06-06T00:06:52.213Z",
    "simTime": "Dia 5 - 8:00 AM",
    "dailyCost": 2,
    "totalCost": 16.770508463698874,
    "totalRevenue": 67.5,
    "profit": 50.729491536301126
  },
  {
    "timestamp": "2026-06-06T00:06:54.215Z",
    "simTime": "Dia 5 - 8:06 AM",
    "dailyCost": 2,
    "totalCost": 16.780331095324236,
    "totalRevenue": 67.5,
    "profit": 50.719668904675764
  },
  {
    "timestamp": "2026-06-06T00:06:56.219Z",
    "simTime": "Dia 5 - 8:12 AM",
    "dailyCost": 2,
    "totalCost": 16.790153789205455,
    "totalRevenue": 67.5,
    "profit": 50.709846210794545
  },
  {
    "timestamp": "2026-06-06T00:06:58.218Z",
    "simTime": "Dia 5 - 8:18 AM",
    "dailyCost": 2,
    "totalCost": 16.799976545342535,
    "totalRevenue": 67.5,
    "profit": 50.70002345465747
  },
  {
    "timestamp": "2026-06-06T00:07:00.232Z",
    "simTime": "Dia 5 - 8:24 AM",
    "dailyCost": 2,
    "totalCost": 16.809799363735472,
    "totalRevenue": 67.5,
    "profit": 50.69020063626453
  },
  {
    "timestamp": "2026-06-06T00:07:02.246Z",
    "simTime": "Dia 5 - 8:30 AM",
    "dailyCost": 2,
    "totalCost": 16.81962224438427,
    "totalRevenue": 67.5,
    "profit": 50.68037775561573
  },
  {
    "timestamp": "2026-06-06T00:07:04.259Z",
    "simTime": "Dia 5 - 8:36 AM",
    "dailyCost": 2,
    "totalCost": 16.829445187288925,
    "totalRevenue": 67.5,
    "profit": 50.670554812711075
  },
  {
    "timestamp": "2026-06-06T00:07:06.262Z",
    "simTime": "Dia 5 - 8:42 AM",
    "dailyCost": 2,
    "totalCost": 16.839268192449442,
    "totalRevenue": 67.5,
    "profit": 50.66073180755056
  },
  {
    "timestamp": "2026-06-06T00:07:08.270Z",
    "simTime": "Dia 5 - 8:48 AM",
    "dailyCost": 2,
    "totalCost": 16.84909125986582,
    "totalRevenue": 67.5,
    "profit": 50.650908740134184
  },
  {
    "timestamp": "2026-06-06T00:07:10.276Z",
    "simTime": "Dia 5 - 8:54 AM",
    "dailyCost": 2,
    "totalCost": 16.858914389538054,
    "totalRevenue": 67.5,
    "profit": 50.64108561046194
  },
  {
    "timestamp": "2026-06-06T00:07:12.279Z",
    "simTime": "Dia 5 - 9:00 AM",
    "dailyCost": 2,
    "totalCost": 16.86873758146615,
    "totalRevenue": 67.5,
    "profit": 50.63126241853385
  },
  {
    "timestamp": "2026-06-06T00:07:14.296Z",
    "simTime": "Dia 5 - 9:06 AM",
    "dailyCost": 2,
    "totalCost": 16.878560861437325,
    "totalRevenue": 67.5,
    "profit": 50.62143913856268
  },
  {
    "timestamp": "2026-06-06T00:07:16.312Z",
    "simTime": "Dia 5 - 9:12 AM",
    "dailyCost": 2,
    "totalCost": 16.88838422945158,
    "totalRevenue": 67.5,
    "profit": 50.61161577054842
  },
  {
    "timestamp": "2026-06-06T00:07:18.326Z",
    "simTime": "Dia 5 - 9:18 AM",
    "dailyCost": 2,
    "totalCost": 16.89820768550892,
    "totalRevenue": 67.5,
    "profit": 50.60179231449108
  },
  {
    "timestamp": "2026-06-06T00:07:20.347Z",
    "simTime": "Dia 5 - 9:24 AM",
    "dailyCost": 2,
    "totalCost": 16.908031229609335,
    "totalRevenue": 67.5,
    "profit": 50.591968770390665
  },
  {
    "timestamp": "2026-06-06T00:07:22.346Z",
    "simTime": "Dia 5 - 9:30 AM",
    "dailyCost": 2,
    "totalCost": 16.917854861752833,
    "totalRevenue": 67.5,
    "profit": 50.58214513824717
  },
  {
    "timestamp": "2026-06-06T00:07:24.347Z",
    "simTime": "Dia 5 - 9:36 AM",
    "dailyCost": 2,
    "totalCost": 16.92767858193941,
    "totalRevenue": 67.5,
    "profit": 50.57232141806059
  },
  {
    "timestamp": "2026-06-06T00:07:26.353Z",
    "simTime": "Dia 5 - 9:42 AM",
    "dailyCost": 2,
    "totalCost": 16.93750239016907,
    "totalRevenue": 67.5,
    "profit": 50.56249760983093
  },
  {
    "timestamp": "2026-06-06T00:07:28.357Z",
    "simTime": "Dia 5 - 9:48 AM",
    "dailyCost": 2,
    "totalCost": 16.947326286441807,
    "totalRevenue": 67.5,
    "profit": 50.55267371355819
  },
  {
    "timestamp": "2026-06-06T00:07:30.358Z",
    "simTime": "Dia 5 - 9:54 AM",
    "dailyCost": 2,
    "totalCost": 16.957150270757626,
    "totalRevenue": 67.5,
    "profit": 50.54284972924238
  },
  {
    "timestamp": "2026-06-06T00:07:32.369Z",
    "simTime": "Dia 5 - 10:00 AM",
    "dailyCost": 2,
    "totalCost": 16.96697434311653,
    "totalRevenue": 67.5,
    "profit": 50.53302565688347
  },
  {
    "timestamp": "2026-06-06T00:07:34.388Z",
    "simTime": "Dia 5 - 10:06 AM",
    "dailyCost": 2,
    "totalCost": 16.976798523305742,
    "totalRevenue": 67.5,
    "profit": 50.523201476694254
  },
  {
    "timestamp": "2026-06-06T00:07:36.388Z",
    "simTime": "Dia 5 - 10:12 AM",
    "dailyCost": 2,
    "totalCost": 16.986622811325265,
    "totalRevenue": 67.5,
    "profit": 50.51337718867474
  },
  {
    "timestamp": "2026-06-06T00:07:38.394Z",
    "simTime": "Dia 5 - 10:18 AM",
    "dailyCost": 2,
    "totalCost": 16.996447207175102,
    "totalRevenue": 67.5,
    "profit": 50.5035527928249
  },
  {
    "timestamp": "2026-06-06T00:07:40.401Z",
    "simTime": "Dia 5 - 10:24 AM",
    "dailyCost": 2,
    "totalCost": 17.00627171085525,
    "totalRevenue": 67.5,
    "profit": 50.493728289144755
  },
  {
    "timestamp": "2026-06-06T00:07:42.404Z",
    "simTime": "Dia 5 - 10:30 AM",
    "dailyCost": 2,
    "totalCost": 17.01609632236571,
    "totalRevenue": 67.5,
    "profit": 50.48390367763429
  },
  {
    "timestamp": "2026-06-06T00:07:44.404Z",
    "simTime": "Dia 5 - 10:36 AM",
    "dailyCost": 2,
    "totalCost": 17.02592104170648,
    "totalRevenue": 67.5,
    "profit": 50.47407895829352
  },
  {
    "timestamp": "2026-06-06T00:07:46.419Z",
    "simTime": "Dia 5 - 10:42 AM",
    "dailyCost": 2,
    "totalCost": 17.03574586887756,
    "totalRevenue": 67.5,
    "profit": 50.464254131122445
  },
  {
    "timestamp": "2026-06-06T00:07:48.420Z",
    "simTime": "Dia 5 - 10:48 AM",
    "dailyCost": 2,
    "totalCost": 17.045570803878952,
    "totalRevenue": 67.5,
    "profit": 50.45442919612105
  },
  {
    "timestamp": "2026-06-06T00:07:50.435Z",
    "simTime": "Dia 5 - 10:54 AM",
    "dailyCost": 2,
    "totalCost": 17.055395846710656,
    "totalRevenue": 67.5,
    "profit": 50.44460415328935
  },
  {
    "timestamp": "2026-06-06T00:07:52.439Z",
    "simTime": "Dia 5 - 11:00 AM",
    "dailyCost": 2,
    "totalCost": 17.065220997372673,
    "totalRevenue": 67.5,
    "profit": 50.43477900262732
  },
  {
    "timestamp": "2026-06-06T00:07:54.447Z",
    "simTime": "Dia 5 - 11:06 AM",
    "dailyCost": 2,
    "totalCost": 17.075046268303776,
    "totalRevenue": 67.5,
    "profit": 50.42495373169622
  },
  {
    "timestamp": "2026-06-06T00:07:56.447Z",
    "simTime": "Dia 5 - 11:12 AM",
    "dailyCost": 2,
    "totalCost": 17.08487165950396,
    "totalRevenue": 67.5,
    "profit": 50.41512834049604
  },
  {
    "timestamp": "2026-06-06T00:07:58.455Z",
    "simTime": "Dia 5 - 11:18 AM",
    "dailyCost": 2,
    "totalCost": 17.09469717097323,
    "totalRevenue": 67.5,
    "profit": 50.405302829026766
  },
  {
    "timestamp": "2026-06-06T00:08:00.469Z",
    "simTime": "Dia 5 - 11:24 AM",
    "dailyCost": 2,
    "totalCost": 17.104522802711585,
    "totalRevenue": 67.5,
    "profit": 50.395477197288415
  },
  {
    "timestamp": "2026-06-06T00:08:02.483Z",
    "simTime": "Dia 5 - 11:30 AM",
    "dailyCost": 2,
    "totalCost": 17.114348554719026,
    "totalRevenue": 67.5,
    "profit": 50.38565144528097
  },
  {
    "timestamp": "2026-06-06T00:08:04.499Z",
    "simTime": "Dia 5 - 11:36 AM",
    "dailyCost": 2,
    "totalCost": 17.124174426995552,
    "totalRevenue": 67.5,
    "profit": 50.37582557300445
  },
  {
    "timestamp": "2026-06-06T00:09:01.608Z",
    "simTime": "Dia 1 - 12:06 AM",
    "dailyCost": 1,
    "totalCost": 0.016618276285872573,
    "totalRevenue": 562.5197757382433,
    "profit": 562.5031574619575
  },
  {
    "timestamp": "2026-06-06T00:09:03.611Z",
    "simTime": "Dia 1 - 12:12 AM",
    "dailyCost": 1,
    "totalCost": 0.033235947434319846,
    "totalRevenue": 562.539316041484,
    "profit": 562.5060800940497
  },
  {
    "timestamp": "2026-06-06T00:09:05.621Z",
    "simTime": "Dia 1 - 12:18 AM",
    "dailyCost": 1,
    "totalCost": 0.049853008165919865,
    "totalRevenue": 562.5586210565768,
    "profit": 562.508768048411
  },
  {
    "timestamp": "2026-06-06T00:09:07.627Z",
    "simTime": "Dia 1 - 12:24 AM",
    "dailyCost": 1,
    "totalCost": 0.06646945320580949,
    "totalRevenue": 562.5776909306875,
    "profit": 562.5112214774816
  },
  {
    "timestamp": "2026-06-06T00:09:09.631Z",
    "simTime": "Dia 1 - 12:30 AM",
    "dailyCost": 1,
    "totalCost": 0.08308527728369017,
    "totalRevenue": 562.5965258112917,
    "profit": 562.513440534008
  },
  {
    "timestamp": "2026-06-06T00:09:11.638Z",
    "simTime": "Dia 1 - 12:36 AM",
    "dailyCost": 1,
    "totalCost": 0.09970047513383368,
    "totalRevenue": 562.615125846174,
    "profit": 562.5154253710401
  },
  {
    "timestamp": "2026-06-06T00:09:13.643Z",
    "simTime": "Dia 1 - 12:42 AM",
    "dailyCost": 1,
    "totalCost": 0.11631504149508787,
    "totalRevenue": 562.6334911834279,
    "profit": 562.5171761419327
  },
  {
    "timestamp": "2026-06-06T00:09:15.654Z",
    "simTime": "Dia 1 - 12:48 AM",
    "dailyCost": 1,
    "totalCost": 0.13292897111088237,
    "totalRevenue": 562.6516219714539,
    "profit": 562.518693000343
  },
  {
    "timestamp": "2026-06-06T00:09:17.655Z",
    "simTime": "Dia 1 - 12:54 AM",
    "dailyCost": 1,
    "totalCost": 0.14954225872923427,
    "totalRevenue": 562.6695183589599,
    "profit": 562.5199761002307
  },
  {
    "timestamp": "2026-06-06T00:09:19.665Z",
    "simTime": "Dia 1 - 1:00 AM",
    "dailyCost": 1,
    "totalCost": 0.1661548991027538,
    "totalRevenue": 562.6871804949596,
    "profit": 562.5210255958569
  },
  {
    "timestamp": "2026-06-06T00:09:21.676Z",
    "simTime": "Dia 1 - 1:06 AM",
    "dailyCost": 1,
    "totalCost": 0.1827669223578889,
    "totalRevenue": 562.7046085783118,
    "profit": 562.5218416559538
  },
  {
    "timestamp": "2026-06-06T00:09:23.683Z",
    "simTime": "Dia 1 - 1:12 AM",
    "dailyCost": 1,
    "totalCost": 0.1993783232596658,
    "totalRevenue": 562.7218027566453,
    "profit": 562.5224244333856
  },
  {
    "timestamp": "2026-06-06T00:09:25.689Z",
    "simTime": "Dia 1 - 1:18 AM",
    "dailyCost": 1,
    "totalCost": 0.2159890965776323,
    "totalRevenue": 562.7387631778948,
    "profit": 562.5227740813172
  },
  {
    "timestamp": "2026-06-06T00:09:27.699Z",
    "simTime": "Dia 1 - 1:24 AM",
    "dailyCost": 1,
    "totalCost": 0.23259923708586355,
    "totalRevenue": 562.7554899902996,
    "profit": 562.5228907532137
  },
  {
    "timestamp": "2026-06-06T00:09:29.703Z",
    "simTime": "Dia 1 - 1:30 AM",
    "dailyCost": 1,
    "totalCost": 0.24920873956296768,
    "totalRevenue": 562.7719833424021,
    "profit": 562.5227746028391
  },
  {
    "timestamp": "2026-06-06T00:09:31.703Z",
    "simTime": "Dia 1 - 1:36 AM",
    "dailyCost": 1,
    "totalCost": 0.26581759879209144,
    "totalRevenue": 562.7882433830484,
    "profit": 562.5224257842564
  },
  {
    "timestamp": "2026-06-06T00:09:33.705Z",
    "simTime": "Dia 1 - 1:42 AM",
    "dailyCost": 1,
    "totalCost": 0.28242580956092583,
    "totalRevenue": 562.8042702613866,
    "profit": 562.5218444518257
  },
  {
    "timestamp": "2026-06-06T00:09:35.723Z",
    "simTime": "Dia 1 - 1:48 AM",
    "dailyCost": 1,
    "totalCost": 0.29903336666171165,
    "totalRevenue": 562.8200641268662,
    "profit": 562.5210307602046
  },
  {
    "timestamp": "2026-06-06T00:09:37.738Z",
    "simTime": "Dia 1 - 1:54 AM",
    "dailyCost": 1,
    "totalCost": 0.31564026489124514,
    "totalRevenue": 562.8356251292377,
    "profit": 562.5199848643464
  },
  {
    "timestamp": "2026-06-06T00:09:39.754Z",
    "simTime": "Dia 1 - 2:00 AM",
    "dailyCost": 1,
    "totalCost": 0.33224649905088355,
    "totalRevenue": 562.8509534185512,
    "profit": 562.5187069195002
  },
  {
    "timestamp": "2026-06-06T00:09:41.754Z",
    "simTime": "Dia 1 - 2:06 AM",
    "dailyCost": 1,
    "totalCost": 0.34885216767323235,
    "totalRevenue": 562.8660492710712,
    "profit": 562.517197103398
  },
  {
    "timestamp": "2026-06-06T00:09:43.753Z",
    "simTime": "Dia 1 - 2:12 AM",
    "dailyCost": 1,
    "totalCost": 0.3654572655769186,
    "totalRevenue": 562.8809128316205,
    "profit": 562.5154555660437
  },
  {
    "timestamp": "2026-06-06T00:09:45.760Z",
    "simTime": "Dia 1 - 2:18 AM",
    "dailyCost": 1,
    "totalCost": 0.3820617875848894,
    "totalRevenue": 562.8955442453247,
    "profit": 562.5134824577398
  },
  {
    "timestamp": "2026-06-06T00:09:47.775Z",
    "simTime": "Dia 1 - 2:24 AM",
    "dailyCost": 1,
    "totalCost": 0.39866572852441745,
    "totalRevenue": 562.9099436576103,
    "profit": 562.5112779290858
  },
  {
    "timestamp": "2026-06-06T00:09:49.788Z",
    "simTime": "Dia 1 - 2:30 AM",
    "dailyCost": 1,
    "totalCost": 0.415269083227107,
    "totalRevenue": 562.9241112142047,
    "profit": 562.5088421309775
  },
  {
    "timestamp": "2026-06-06T00:09:51.803Z",
    "simTime": "Dia 1 - 2:36 AM",
    "dailyCost": 1,
    "totalCost": 0.4318718465288992,
    "totalRevenue": 562.9380470611356,
    "profit": 562.5061752146067
  },
  {
    "timestamp": "2026-06-06T00:09:53.814Z",
    "simTime": "Dia 1 - 2:42 AM",
    "dailyCost": 1,
    "totalCost": 0.44847401327007824,
    "totalRevenue": 562.9517513447302,
    "profit": 562.50327733146
  },
  {
    "timestamp": "2026-06-06T00:09:55.816Z",
    "simTime": "Dia 1 - 2:48 AM",
    "dailyCost": 1,
    "totalCost": 0.4650755782952766,
    "totalRevenue": 562.9652242116138,
    "profit": 562.5001486333185
  },
  {
    "timestamp": "2026-06-06T00:09:57.819Z",
    "simTime": "Dia 1 - 2:54 AM",
    "dailyCost": 1,
    "totalCost": 0.481676536453481,
    "totalRevenue": 562.9784658087096,
    "profit": 562.4967892722561
  },
  {
    "timestamp": "2026-06-06T00:09:59.830Z",
    "simTime": "Dia 1 - 3:00 AM",
    "dailyCost": 1,
    "totalCost": 0.4982768825980377,
    "totalRevenue": 562.9914762832382,
    "profit": 562.4931994006402
  },
  {
    "timestamp": "2026-06-06T00:10:01.829Z",
    "simTime": "Dia 1 - 3:06 AM",
    "dailyCost": 1,
    "totalCost": 0.5148767766318161,
    "totalRevenue": 563.0042559524212,
    "profit": 562.4893791757894
  },
  {
    "timestamp": "2026-06-06T00:10:03.830Z",
    "simTime": "Dia 1 - 3:12 AM",
    "dailyCost": 1,
    "totalCost": 0.531476213427799,
    "totalRevenue": 563.016804954841,
    "profit": 562.4853287414131
  },
  {
    "timestamp": "2026-06-06T00:10:05.830Z",
    "simTime": "Dia 1 - 3:18 AM",
    "dailyCost": 1,
    "totalCost": 0.548075187862939,
    "totalRevenue": 563.0291234293823,
    "profit": 562.4810482415193
  },
  {
    "timestamp": "2026-06-06T00:10:07.846Z",
    "simTime": "Dia 1 - 3:24 AM",
    "dailyCost": 1,
    "totalCost": 0.5646736948181633,
    "totalRevenue": 563.0412115152315,
    "profit": 562.4765378204133
  },
  {
    "timestamp": "2026-06-06T00:10:09.847Z",
    "simTime": "Dia 1 - 3:30 AM",
    "dailyCost": 1,
    "totalCost": 0.5812717291783808,
    "totalRevenue": 563.0530693518757,
    "profit": 562.4717976226973
  },
  {
    "timestamp": "2026-06-06T00:10:11.856Z",
    "simTime": "Dia 1 - 3:36 AM",
    "dailyCost": 1,
    "totalCost": 0.5978692858324872,
    "totalRevenue": 563.0646970791026,
    "profit": 562.4668277932701
  },
  {
    "timestamp": "2026-06-06T00:10:13.858Z",
    "simTime": "Dia 1 - 3:42 AM",
    "dailyCost": 1,
    "totalCost": 0.6144663596733715,
    "totalRevenue": 563.0760948369988,
    "profit": 562.4616284773255
  },
  {
    "timestamp": "2026-06-06T00:10:15.859Z",
    "simTime": "Dia 1 - 3:48 AM",
    "dailyCost": 1,
    "totalCost": 0.6310629455979211,
    "totalRevenue": 563.08726276595,
    "profit": 562.456199820352
  },
  {
    "timestamp": "2026-06-06T00:10:17.862Z",
    "simTime": "Dia 1 - 3:54 AM",
    "dailyCost": 1,
    "totalCost": 0.6476590385070283,
    "totalRevenue": 563.0982010066399,
    "profit": 562.4505419681328
  },
  {
    "timestamp": "2026-06-06T00:10:19.865Z",
    "simTime": "Dia 1 - 4:00 AM",
    "dailyCost": 1,
    "totalCost": 0.6642546333055961,
    "totalRevenue": 563.1089097000496,
    "profit": 562.444655066744
  },
  {
    "timestamp": "2026-06-06T00:10:21.877Z",
    "simTime": "Dia 1 - 4:06 AM",
    "dailyCost": 1,
    "totalCost": 0.6808499400366866,
    "totalRevenue": 563.119389168941,
    "profit": 562.4385392289043
  },
  {
    "timestamp": "2026-06-06T00:10:23.877Z",
    "simTime": "Dia 1 - 4:12 AM",
    "dailyCost": 1,
    "totalCost": 0.6974449536248136,
    "totalRevenue": 563.1296395429065,
    "profit": 562.4321945892817
  },
  {
    "timestamp": "2026-06-06T00:10:25.878Z",
    "simTime": "Dia 1 - 4:18 AM",
    "dailyCost": 1,
    "totalCost": 0.7140396689979912,
    "totalRevenue": 563.1396609518433,
    "profit": 562.4256212828453
  },
  {
    "timestamp": "2026-06-06T00:10:27.884Z",
    "simTime": "Dia 1 - 4:24 AM",
    "dailyCost": 1,
    "totalCost": 0.7306340810877403,
    "totalRevenue": 563.1494535259533,
    "profit": 562.4188194448656
  },
  {
    "timestamp": "2026-06-06T00:10:29.884Z",
    "simTime": "Dia 1 - 4:30 AM",
    "dailyCost": 1,
    "totalCost": 0.7472281848290951,
    "totalRevenue": 563.1590173957414,
    "profit": 562.4117892109124
  },
  {
    "timestamp": "2026-06-06T00:10:31.885Z",
    "simTime": "Dia 1 - 4:36 AM",
    "dailyCost": 1,
    "totalCost": 0.763821975160609,
    "totalRevenue": 563.1683526920157,
    "profit": 562.4045307168551
  },
  {
    "timestamp": "2026-06-06T00:10:33.894Z",
    "simTime": "Dia 1 - 4:42 AM",
    "dailyCost": 1,
    "totalCost": 0.7804154470243607,
    "totalRevenue": 563.1774595458868,
    "profit": 562.3970440988625
  },
  {
    "timestamp": "2026-06-06T00:10:35.902Z",
    "simTime": "Dia 1 - 4:48 AM",
    "dailyCost": 1,
    "totalCost": 0.7970085953659608,
    "totalRevenue": 563.1863380887667,
    "profit": 562.3893294934007
  },
  {
    "timestamp": "2026-06-06T00:10:37.904Z",
    "simTime": "Dia 1 - 4:54 AM",
    "dailyCost": 1,
    "totalCost": 0.8136014151345574,
    "totalRevenue": 563.1949884523684,
    "profit": 562.3813870372338
  },
  {
    "timestamp": "2026-06-06T00:10:39.909Z",
    "simTime": "Dia 1 - 5:00 AM",
    "dailyCost": 1,
    "totalCost": 0.8301939012828429,
    "totalRevenue": 563.2034107687058,
    "profit": 562.3732168674229
  },
  {
    "timestamp": "2026-06-06T00:10:41.917Z",
    "simTime": "Dia 1 - 5:06 AM",
    "dailyCost": 1,
    "totalCost": 0.846786299336085,
    "totalRevenue": 563.2116053354532,
    "profit": 562.3648190361172
  },
  {
    "timestamp": "2026-06-06T00:10:43.919Z",
    "simTime": "Dia 1 - 5:12 AM",
    "dailyCost": 1,
    "totalCost": 0.863378604264512,
    "totalRevenue": 563.2195722713254,
    "profit": 562.3561936670609
  },
  {
    "timestamp": "2026-06-06T00:10:45.932Z",
    "simTime": "Dia 1 - 5:18 AM",
    "dailyCost": 1,
    "totalCost": 0.879970811041304,
    "totalRevenue": 563.227311695346,
    "profit": 562.3473408843047
  },
  {
    "timestamp": "2026-06-06T00:10:47.947Z",
    "simTime": "Dia 1 - 5:24 AM",
    "dailyCost": 1,
    "totalCost": 0.8965629146425999,
    "totalRevenue": 563.2348237268477,
    "profit": 562.3382608122051
  },
  {
    "timestamp": "2026-06-06T00:10:49.960Z",
    "simTime": "Dia 1 - 5:30 AM",
    "dailyCost": 1,
    "totalCost": 0.913154910047503,
    "totalRevenue": 563.2421084854717,
    "profit": 562.3289535754242
  },
  {
    "timestamp": "2026-06-06T00:10:51.967Z",
    "simTime": "Dia 1 - 5:36 AM",
    "dailyCost": 1,
    "totalCost": 0.9297467922380888,
    "totalRevenue": 563.2491660911668,
    "profit": 562.3194192989287
  },
  {
    "timestamp": "2026-06-06T00:10:53.970Z",
    "simTime": "Dia 1 - 5:42 AM",
    "dailyCost": 1,
    "totalCost": 0.9463385561994104,
    "totalRevenue": 563.2559966641892,
    "profit": 562.3096581079898
  },
  {
    "timestamp": "2026-06-06T00:10:55.971Z",
    "simTime": "Dia 1 - 5:48 AM",
    "dailyCost": 1,
    "totalCost": 0.962930196919506,
    "totalRevenue": 563.2626003251012,
    "profit": 562.2996701281817
  },
  {
    "timestamp": "2026-06-06T00:10:57.975Z",
    "simTime": "Dia 1 - 5:54 AM",
    "dailyCost": 1,
    "totalCost": 0.9795217093894045,
    "totalRevenue": 563.2689771947714,
    "profit": 562.2894554853821
  },
  {
    "timestamp": "2026-06-06T00:10:59.988Z",
    "simTime": "Dia 1 - 6:00 AM",
    "dailyCost": 1,
    "totalCost": 0.996113088603133,
    "totalRevenue": 563.2751273943741,
    "profit": 562.2790143057709
  },
  {
    "timestamp": "2026-06-06T00:11:01.997Z",
    "simTime": "Dia 1 - 6:06 AM",
    "dailyCost": 1,
    "totalCost": 1.0127045984834793,
    "totalRevenue": 563.2810511737391,
    "profit": 562.2683465752557
  },
  {
    "timestamp": "2026-06-06T00:11:03.998Z",
    "simTime": "Dia 1 - 6:12 AM",
    "dailyCost": 1,
    "totalCost": 1.0292962340384284,
    "totalRevenue": 563.286748639793,
    "profit": 562.2574524057546
  },
  {
    "timestamp": "2026-06-06T00:11:06.009Z",
    "simTime": "Dia 1 - 6:18 AM",
    "dailyCost": 1,
    "totalCost": 1.0458879902783311,
    "totalRevenue": 563.2922198997775,
    "profit": 562.2463319094992
  },
  {
    "timestamp": "2026-06-06T00:11:08.021Z",
    "simTime": "Dia 1 - 6:24 AM",
    "dailyCost": 1,
    "totalCost": 1.0624798622159104,
    "totalRevenue": 563.2974650612489,
    "profit": 562.234985199033
  },
  {
    "timestamp": "2026-06-06T00:11:10.034Z",
    "simTime": "Dia 1 - 6:30 AM",
    "dailyCost": 1,
    "totalCost": 1.0790718448662688,
    "totalRevenue": 563.3024842320779,
    "profit": 562.2234123872116
  },
  {
    "timestamp": "2026-06-06T00:11:12.034Z",
    "simTime": "Dia 1 - 6:36 AM",
    "dailyCost": 1,
    "totalCost": 1.0956639332468954,
    "totalRevenue": 563.3072775204494,
    "profit": 562.2116135872025
  },
  {
    "timestamp": "2026-06-06T00:11:14.035Z",
    "simTime": "Dia 1 - 6:42 AM",
    "dailyCost": 1,
    "totalCost": 1.112256122377672,
    "totalRevenue": 563.3118450348607,
    "profit": 562.199588912483
  },
  {
    "timestamp": "2026-06-06T00:11:16.038Z",
    "simTime": "Dia 1 - 6:48 AM",
    "dailyCost": 1,
    "totalCost": 1.1288484072808809,
    "totalRevenue": 563.3161868841225,
    "profit": 562.1873384768417
  },
  {
    "timestamp": "2026-06-06T00:11:18.040Z",
    "simTime": "Dia 1 - 6:54 AM",
    "dailyCost": 1,
    "totalCost": 1.1454407829812112,
    "totalRevenue": 563.3203031773577,
    "profit": 562.1748623943765
  },
  {
    "timestamp": "2026-06-06T00:11:20.054Z",
    "simTime": "Dia 1 - 7:00 AM",
    "dailyCost": 1,
    "totalCost": 1.1620332445057664,
    "totalRevenue": 563.3241940240007,
    "profit": 562.1621607794949
  },
  {
    "timestamp": "2026-06-06T00:11:22.063Z",
    "simTime": "Dia 1 - 7:06 AM",
    "dailyCost": 1,
    "totalCost": 1.1786260558310966,
    "totalRevenue": 563.3278596132815,
    "profit": 562.1492335574504
  },
  {
    "timestamp": "2026-06-06T00:11:24.079Z",
    "simTime": "Dia 1 - 7:12 AM",
    "dailyCost": 1,
    "totalCost": 1.1952192119938654,
    "totalRevenue": 563.331300040456,
    "profit": 562.1360808284621
  },
  {
    "timestamp": "2026-06-06T00:11:26.089Z",
    "simTime": "Dia 1 - 7:18 AM",
    "dailyCost": 1,
    "totalCost": 1.211812708032522,
    "totalRevenue": 563.3345154011018,
    "profit": 562.1227026930693
  },
  {
    "timestamp": "2026-06-06T00:11:28.090Z",
    "simTime": "Dia 1 - 7:24 AM",
    "dailyCost": 1,
    "totalCost": 1.228406538987309,
    "totalRevenue": 563.3375057911179,
    "profit": 562.1090992521306
  },
  {
    "timestamp": "2026-06-06T00:11:30.099Z",
    "simTime": "Dia 1 - 7:30 AM",
    "dailyCost": 1,
    "totalCost": 1.245000699900269,
    "totalRevenue": 563.3402713067233,
    "profit": 562.095270606823
  },
  {
    "timestamp": "2026-06-06T00:11:32.102Z",
    "simTime": "Dia 1 - 7:36 AM",
    "dailyCost": 1,
    "totalCost": 1.2615951858152528,
    "totalRevenue": 563.3428120444577,
    "profit": 562.0812168586424
  },
  {
    "timestamp": "2026-06-06T00:11:34.105Z",
    "simTime": "Dia 1 - 7:42 AM",
    "dailyCost": 1,
    "totalCost": 1.2781899917779258,
    "totalRevenue": 563.3451281011804,
    "profit": 562.0669381094025
  },
  {
    "timestamp": "2026-06-06T00:11:36.105Z",
    "simTime": "Dia 1 - 7:48 AM",
    "dailyCost": 1,
    "totalCost": 1.2947851128357757,
    "totalRevenue": 563.3472195740702,
    "profit": 562.0524344612344
  },
  {
    "timestamp": "2026-06-06T00:11:38.106Z",
    "simTime": "Dia 1 - 7:54 AM",
    "dailyCost": 1,
    "totalCost": 1.3113805440381192,
    "totalRevenue": 563.3490865606244,
    "profit": 562.0377060165863
  },
  {
    "timestamp": "2026-06-06T00:11:40.106Z",
    "simTime": "Dia 1 - 8:00 AM",
    "dailyCost": 1,
    "totalCost": 1.32797628043611,
    "totalRevenue": 563.3507291586593,
    "profit": 562.0227528782232
  },
  {
    "timestamp": "2026-06-06T00:11:42.110Z",
    "simTime": "Dia 1 - 8:06 AM",
    "dailyCost": 1,
    "totalCost": 1.344572567711282,
    "totalRevenue": 563.3521474950562,
    "profit": 562.0075749273449
  },
  {
    "timestamp": "2026-06-06T00:11:44.114Z",
    "simTime": "Dia 1 - 8:12 AM",
    "dailyCost": 1,
    "totalCost": 1.3611694009198776,
    "totalRevenue": 563.3533416545263,
    "profit": 561.9921722536064
  },
  {
    "timestamp": "2026-06-06T00:11:46.126Z",
    "simTime": "Dia 1 - 8:18 AM",
    "dailyCost": 1,
    "totalCost": 1.3777667751193945,
    "totalRevenue": 563.3543117221082,
    "profit": 561.9765449469887
  },
  {
    "timestamp": "2026-06-06T00:11:48.126Z",
    "simTime": "Dia 1 - 8:24 AM",
    "dailyCost": 1,
    "totalCost": 1.3943646853685947,
    "totalRevenue": 563.3550577831679,
    "profit": 561.9606930977993
  },
  {
    "timestamp": "2026-06-06T00:11:50.137Z",
    "simTime": "Dia 1 - 8:30 AM",
    "dailyCost": 1,
    "totalCost": 1.410963126727511,
    "totalRevenue": 563.355579923398,
    "profit": 561.9446167966704
  },
  {
    "timestamp": "2026-06-06T00:11:52.142Z",
    "simTime": "Dia 1 - 8:36 AM",
    "dailyCost": 1,
    "totalCost": 1.4275620942574547,
    "totalRevenue": 563.3558782288175,
    "profit": 561.92831613456
  },
  {
    "timestamp": "2026-06-06T00:11:54.147Z",
    "simTime": "Dia 1 - 8:42 AM",
    "dailyCost": 1,
    "totalCost": 1.4441615830210242,
    "totalRevenue": 563.355952785771,
    "profit": 561.91179120275
  },
  {
    "timestamp": "2026-06-06T00:11:56.152Z",
    "simTime": "Dia 1 - 8:48 AM",
    "dailyCost": 1,
    "totalCost": 1.4607615913728746,
    "totalRevenue": 563.355952785771,
    "profit": 561.8951911943982
  },
  {
    "timestamp": "2026-06-06T00:11:58.166Z",
    "simTime": "Dia 1 - 8:54 AM",
    "dailyCost": 1,
    "totalCost": 1.4773621193130062,
    "totalRevenue": 563.355952785771,
    "profit": 561.878590666458
  },
  {
    "timestamp": "2026-06-06T00:12:00.180Z",
    "simTime": "Dia 1 - 9:00 AM",
    "dailyCost": 1,
    "totalCost": 1.493963166841419,
    "totalRevenue": 563.355952785771,
    "profit": 561.8619896189296
  },
  {
    "timestamp": "2026-06-06T00:12:02.184Z",
    "simTime": "Dia 1 - 9:06 AM",
    "dailyCost": 1,
    "totalCost": 1.5105649491786257,
    "totalRevenue": 563.355952785771,
    "profit": 561.8453878365924
  },
  {
    "timestamp": "2026-06-06T00:12:04.189Z",
    "simTime": "Dia 1 - 9:12 AM",
    "dailyCost": 1,
    "totalCost": 1.5271674663246264,
    "totalRevenue": 563.355952785771,
    "profit": 561.8287853194464
  },
  {
    "timestamp": "2026-06-06T00:12:06.191Z",
    "simTime": "Dia 1 - 9:18 AM",
    "dailyCost": 1,
    "totalCost": 1.5437707182794211,
    "totalRevenue": 563.355952785771,
    "profit": 561.8121820674916
  },
  {
    "timestamp": "2026-06-06T00:12:08.205Z",
    "simTime": "Dia 1 - 9:24 AM",
    "dailyCost": 1,
    "totalCost": 1.56037470504301,
    "totalRevenue": 563.355952785771,
    "profit": 561.795578080728
  },
  {
    "timestamp": "2026-06-06T00:12:10.212Z",
    "simTime": "Dia 1 - 9:30 AM",
    "dailyCost": 1,
    "totalCost": 1.5769794266153927,
    "totalRevenue": 563.355952785771,
    "profit": 561.7789733591557
  },
  {
    "timestamp": "2026-06-06T00:12:12.212Z",
    "simTime": "Dia 1 - 9:36 AM",
    "dailyCost": 1,
    "totalCost": 1.5935848829965693,
    "totalRevenue": 563.355952785771,
    "profit": 561.7623679027745
  },
  {
    "timestamp": "2026-06-06T00:12:14.216Z",
    "simTime": "Dia 1 - 9:42 AM",
    "dailyCost": 1,
    "totalCost": 1.61019107418654,
    "totalRevenue": 563.355952785771,
    "profit": 561.7457617115845
  },
  {
    "timestamp": "2026-06-06T00:12:16.228Z",
    "simTime": "Dia 1 - 9:48 AM",
    "dailyCost": 1,
    "totalCost": 1.6267980001853046,
    "totalRevenue": 563.355952785771,
    "profit": 561.7291547855857
  },
  {
    "timestamp": "2026-06-06T00:12:18.237Z",
    "simTime": "Dia 1 - 9:54 AM",
    "dailyCost": 1,
    "totalCost": 1.6434056609928633,
    "totalRevenue": 563.355952785771,
    "profit": 561.7125471247782
  },
  {
    "timestamp": "2026-06-06T00:12:20.238Z",
    "simTime": "Dia 1 - 10:00 AM",
    "dailyCost": 1,
    "totalCost": 1.660014056609216,
    "totalRevenue": 563.355952785771,
    "profit": 561.6959387291618
  },
  {
    "timestamp": "2026-06-06T00:12:22.242Z",
    "simTime": "Dia 1 - 10:06 AM",
    "dailyCost": 1,
    "totalCost": 1.6766233521788707,
    "totalRevenue": 563.355952785771,
    "profit": 561.6793294335921
  },
  {
    "timestamp": "2026-06-06T00:12:24.245Z",
    "simTime": "Dia 1 - 10:12 AM",
    "dailyCost": 1,
    "totalCost": 1.6932335477018272,
    "totalRevenue": 563.355952785771,
    "profit": 561.6627192380691
  },
  {
    "timestamp": "2026-06-06T00:12:26.254Z",
    "simTime": "Dia 1 - 10:18 AM",
    "dailyCost": 1,
    "totalCost": 1.7098446431780856,
    "totalRevenue": 563.355952785771,
    "profit": 561.646108142593
  },
  {
    "timestamp": "2026-06-06T00:12:28.269Z",
    "simTime": "Dia 1 - 10:24 AM",
    "dailyCost": 1,
    "totalCost": 1.7264566386076459,
    "totalRevenue": 563.355952785771,
    "profit": 561.6294961471634
  },
  {
    "timestamp": "2026-06-06T00:12:30.292Z",
    "simTime": "Dia 1 - 10:30 AM",
    "dailyCost": 1,
    "totalCost": 1.743069533990508,
    "totalRevenue": 563.355952785771,
    "profit": 561.6128832517805
  },
  {
    "timestamp": "2026-06-06T00:12:32.302Z",
    "simTime": "Dia 1 - 10:36 AM",
    "dailyCost": 1,
    "totalCost": 1.759683329326672,
    "totalRevenue": 563.355952785771,
    "profit": 561.5962694564444
  },
  {
    "timestamp": "2026-06-06T00:12:34.308Z",
    "simTime": "Dia 1 - 10:42 AM",
    "dailyCost": 1,
    "totalCost": 1.776298024616138,
    "totalRevenue": 563.355952785771,
    "profit": 561.5796547611549
  },
  {
    "timestamp": "2026-06-06T00:12:36.322Z",
    "simTime": "Dia 1 - 10:48 AM",
    "dailyCost": 1,
    "totalCost": 1.7929136198589057,
    "totalRevenue": 563.355952785771,
    "profit": 561.5630391659121
  },
  {
    "timestamp": "2026-06-06T00:12:38.333Z",
    "simTime": "Dia 1 - 10:54 AM",
    "dailyCost": 1,
    "totalCost": 1.8095301150549754,
    "totalRevenue": 563.355952785771,
    "profit": 561.5464226707161
  },
  {
    "timestamp": "2026-06-06T00:12:40.347Z",
    "simTime": "Dia 1 - 11:00 AM",
    "dailyCost": 1,
    "totalCost": 1.826147510204347,
    "totalRevenue": 563.355952785771,
    "profit": 561.5298052755667
  },
  {
    "timestamp": "2026-06-06T00:12:42.359Z",
    "simTime": "Dia 1 - 11:06 AM",
    "dailyCost": 1,
    "totalCost": 1.842765909121198,
    "totalRevenue": 563.355952785771,
    "profit": 561.5131868766498
  },
  {
    "timestamp": "2026-06-06T00:12:44.366Z",
    "simTime": "Dia 1 - 11:12 AM",
    "dailyCost": 1,
    "totalCost": 1.8593853118055288,
    "totalRevenue": 563.355952785771,
    "profit": 561.4965674739655
  },
  {
    "timestamp": "2026-06-06T00:12:46.372Z",
    "simTime": "Dia 1 - 11:18 AM",
    "dailyCost": 1,
    "totalCost": 1.8760057182573389,
    "totalRevenue": 563.355952785771,
    "profit": 561.4799470675136
  },
  {
    "timestamp": "2026-06-06T00:12:48.386Z",
    "simTime": "Dia 1 - 11:24 AM",
    "dailyCost": 1,
    "totalCost": 1.8926271284766285,
    "totalRevenue": 563.355952785771,
    "profit": 561.4633256572944
  },
  {
    "timestamp": "2026-06-06T00:12:50.386Z",
    "simTime": "Dia 1 - 11:30 AM",
    "dailyCost": 1,
    "totalCost": 1.9092495424633977,
    "totalRevenue": 563.355952785771,
    "profit": 561.4467032433076
  },
  {
    "timestamp": "2026-06-06T00:12:52.388Z",
    "simTime": "Dia 1 - 11:36 AM",
    "dailyCost": 1,
    "totalCost": 1.9258729602176465,
    "totalRevenue": 563.355952785771,
    "profit": 561.4300798255533
  },
  {
    "timestamp": "2026-06-06T00:12:54.393Z",
    "simTime": "Dia 1 - 11:42 AM",
    "dailyCost": 1,
    "totalCost": 1.9424973817393747,
    "totalRevenue": 563.355952785771,
    "profit": 561.4134554040317
  },
  {
    "timestamp": "2026-06-06T00:12:56.393Z",
    "simTime": "Dia 1 - 11:48 AM",
    "dailyCost": 1,
    "totalCost": 1.9591228070285824,
    "totalRevenue": 563.355952785771,
    "profit": 561.3968299787424
  },
  {
    "timestamp": "2026-06-06T00:12:58.403Z",
    "simTime": "Dia 1 - 11:54 AM",
    "dailyCost": 1,
    "totalCost": 1.9757492360852698,
    "totalRevenue": 563.355952785771,
    "profit": 561.3802035496858
  }
]